{"symbol": "UBER", "frame": "60", "strategy": "Revival2", "mode": "", "realized": 323.95, "change": 34.75, "unrealized": -657.38, "unrealizedValueChange": -6.57, "realizedValueChange": 3.24, "marketValue": 9667, "marketValueChange": -3.33, "tradeNum": 34, "gainNum": 12, "loseNum": 4, "fromDate": "2023-10-24 01:30", "toDate": "2024-04-23 00:30", "regTime": "2024-04-23 01:00", "extend": "", "positionSize": 92, "positionPrice": 75.94, "startingCash": 10000.0, "cash": 3337.89, "arguments": "(BUY:SMA30 SELL:BollTop Cash 10K)"}