{"symbol": "SQ", "frame": "60", "strategy": "Revival2", "mode": "", "realized": 936.01, "change": 107.3, "unrealized": 417.05, "unrealizedValueChange": 4.17, "realizedValueChange": 9.36, "marketValue": 11353, "marketValueChange": 13.53, "tradeNum": 28, "gainNum": 9, "loseNum": 4, "fromDate": "2023-10-13 00:30", "toDate": "2024-04-11 23:30", "regTime": "2024-04-11 23:30", "extend": "", "positionSize": 99, "positionPrice": 73.85, "startingCash": 10000.0, "cash": 3625.12, "arguments": "(BUY:SMA30 SELL:BollTop Cash 10K)"}