{"symbol": "MU", "frame": "60", "strategy": "Revival2", "mode": "", "realized": 1624.89, "change": 173.25, "unrealized": 682.56, "unrealizedValueChange": 6.83, "realizedValueChange": 16.25, "marketValue": 12307, "marketValueChange": 23.07, "tradeNum": 45, "gainNum": 21, "loseNum": 3, "fromDate": "2023-10-13 03:30", "toDate": "2024-04-12 02:30", "regTime": "2024-04-12 02:30", "extend": "", "positionSize": 40, "positionPrice": 109.39, "startingCash": 10000.0, "cash": 7249.41, "arguments": "(BUY:SMA30 SELL:BollTop Cash 10K)"}