{"symbol": "NUGT", "frame": "60", "strategy": "Stoch2", "mode": "", "realized": -158.88, "change": 13.18, "unrealized": 191.07, "unrealizedValueChange": 1.91, "realizedValueChange": -1.59, "marketValue": 10032, "marketValueChange": 0.32, "tradeNum": 61, "gainNum": 21, "loseNum": 12, "fromDate": "2023-10-20 02:30", "toDate": "2024-04-19 01:30", "regTime": "2024-04-19 02:01", "extend": "", "positionSize": 135, "positionPrice": 37.4, "startingCash": 10000.0, "cash": 4791.49, "arguments": "(BollBot x BollTop Cash 10K)"}