{"symbol": "ETN", "frame": "60", "strategy": "Stoch2", "mode": "", "realized": 0.0, "change": 0.0, "unrealized": -1.52, "unrealizedValueChange": -0.02, "realizedValueChange": 0.0, "marketValue": 9998, "marketValueChange": -0.02, "tradeNum": 2, "gainNum": 0, "loseNum": 0, "fromDate": "2023-10-20 02:30", "toDate": "2024-04-19 01:30", "regTime": "2024-04-19 02:01", "extend": "", "positionSize": 8, "positionPrice": 311.14, "startingCash": 10000.0, "cash": 7510.88, "arguments": "(BollBot x BollTop Cash 10K)"}