{"symbol": "MU", "frame": "60", "strategy": "Revival2", "mode": "", "realized": 1453.68, "change": 154.19, "unrealized": 4.98, "unrealizedValueChange": 0.05, "realizedValueChange": 14.54, "marketValue": 11459, "marketValueChange": 14.59, "tradeNum": 47, "gainNum": 18, "loseNum": 5, "fromDate": "2023-11-06 22:30", "toDate": "2024-05-04 03:30", "regTime": "2024-05-04 05:00", "extend": "", "positionSize": 78, "positionPrice": 114.64, "startingCash": 10000.0, "cash": 2512.06, "arguments": "(BUY:SMA30 SELL:BollTop Cash 10K)"}