{"symbol": "PYPL", "frame": "60", "strategy": "Stoch", "mode": "", "realized": 939.86, "change": 273.8, "unrealized": -11.65, "unrealizedValueChange": -0.23, "realizedValueChange": 18.8, "marketValue": 5928, "marketValueChange": 18.56, "tradeNum": 57, "gainNum": 31, "loseNum": 0, "fromDate": "2023-10-17 23:30", "toDate": "2024-04-16 22:30", "regTime": "2024-04-16 23:02", "extend": "", "positionSize": 21, "positionPrice": 64.21, "startingCash": 5000.0, "cash": 4591.35, "arguments": "(BollBot x BollTop TF:60)"}