{"symbol": "TCEHY", "frame": "60", "strategy": "Stoch2", "mode": "", "realized": 2174.59, "change": 216.05, "unrealized": -30.26, "unrealizedValueChange": -0.3, "realizedValueChange": 21.75, "marketValue": 12144, "marketValueChange": 21.44, "tradeNum": 77, "gainNum": 39, "loseNum": 0, "fromDate": "2023-10-18 21:30", "toDate": "2024-04-17 03:00", "regTime": "2024-04-17 03:33", "extend": "", "positionSize": 312, "positionPrice": 38.53, "startingCash": 10000.0, "cash": 154.14, "arguments": "(BollBot x BollTop Cash 10K)"}