{"symbol": "QCOM", "frame": "60", "strategy": "Stoch", "mode": "", "realized": 211.54, "change": 56.89, "unrealized": 0.6, "unrealizedValueChange": 0.01, "realizedValueChange": 4.23, "marketValue": 5212, "marketValueChange": 4.24, "tradeNum": 45, "gainNum": 20, "loseNum": 3, "fromDate": "2023-10-18 01:30", "toDate": "2024-04-17 00:30", "regTime": "2024-04-17 00:32", "extend": "", "positionSize": 2, "positionPrice": 168.14, "startingCash": 5000.0, "cash": 4875.26, "arguments": "(BollBot x BollTop TF:60)"}