{"symbol": "ASML", "frame": "60", "strategy": "Revival2", "mode": "", "realized": 623.27, "change": 87.8, "unrealized": -379.66, "unrealizedValueChange": -3.8, "realizedValueChange": 6.23, "marketValue": 10244, "marketValueChange": 2.44, "tradeNum": 32, "gainNum": 10, "loseNum": 3, "fromDate": "2023-10-25 23:30", "toDate": "2024-04-24 22:30", "regTime": "2024-04-24 23:00", "extend": "", "positionSize": 6, "positionPrice": 961.03, "startingCash": 10000.0, "cash": 4857.09, "arguments": "(BUY:SMA30 SELL:BollTop Cash 10K)"}