[{"symbol": "SOXL", "frame": "60", "strategy": "Stoch", "mode": "", "realized": 1275.59, "change": 448.39, "unrealized": -325.07, "unrealizedValueChange": -6.5, "realizedValueChange": 25.51, "marketValueChange": 19.01, "tradeNum": 90, "fromDate": "2023-05-05 01:30", "toDate": "2023-11-03 00:30", "regTime": "2023-05-18 00:17", "upTime": "2023-11-03 00:30", "extend": "", "positionSize": 251, "positionPrice": 18.18, "startingCash": 5000.0, "cash": 1713.57, "arguments": "(BollBot x BollTop TF:60)"}, {"symbol": "SOXL", "frame": "60", "strategy": "Vivid", "mode": "", "realized": 280.71, "change": 129.06, "unrealized": -725.29, "unrealizedValueChange": -14.51, "realizedValueChange": 5.61, "marketValueChange": -8.89, "tradeNum": 43, "fromDate": "2023-05-05 01:30", "toDate": "2023-11-03 00:30", "regTime": "2023-05-11 22:05", "upTime": "2023-11-03 00:30", "extend": "", "positionSize": 224, "positionPrice": 20.12, "startingCash": 5000.0, "cash": 774.24, "arguments": "(BollBot x BollTop TF:60)"}]