{"items": [{"symbol": "MSFT", "barTime": "2023-05-06 03:30", "content": "SELL@310.65 Size:1 Gain:9.15%", "strategy": "Revival (BUY:SMA30 SELL:BollTop TF:60)", "upTime": "2023-05-07 03:13", "key": 0}, {"symbol": "ASML", "barTime": "2023-05-06 03:30", "content": "SELL@650.32 Size:0 Gain:0.00%", "strategy": "Revival (BUY:SMA30 SELL:BollTop TF:60)", "upTime": "2023-05-07 03:13", "key": 1}, {"symbol": "TCEHY", "barTime": "2023-05-06 03:30", "content": "SELL@43.90 Size:9 Gain:-6.53%", "strategy": "Revival (BUY:SMA30 SELL:BollTop TF:60)", "upTime": "2023-05-07 03:13", "key": 2}, {"symbol": "MSFT", "barTime": "2023-05-06 03:30", "content": "SELL@310.65 Size:1 Gain:11.26%", "strategy": "Vivid (BollBot x BollTop TF:60)", "upTime": "2023-05-07 03:13", "key": 3}, {"symbol": "SMH", "barTime": "2023-05-06 03:30", "content": "SELL@124.38 Size:3 Gain:1.04%", "strategy": "Vivid (BollBot x BollTop TF:60)", "upTime": "2023-05-07 03:30", "key": 4}, {"symbol": "SOXL", "barTime": "2023-05-06 03:30", "content": "SELL@14.47 Size:29 Gain:-2.66%", "strategy": "Vivid (BollBot x BollTop TF:60)", "upTime": "2023-05-07 03:49", "key": 5}, {"symbol": "ASML", "barTime": "2023-05-06 03:30", "content": "SELL@650.32 Size:0 Gain:0.00%", "strategy": "Vivid (BollBot x BollTop TF:60)", "upTime": "2023-05-07 03:13", "key": 6}, {"symbol": "NVDA", "barTime": "2023-05-06 02:30", "content": "SELL@286.82 Size:0 Gain:0.00%", "strategy": "Vivid (BollBot x BollTop TF:60)", "upTime": "2023-05-07 03:49", "key": 7}, {"symbol": "TSLA", "barTime": "2023-05-06 02:30", "content": "SELL@170.16 Size:2 Gain:1.86%", "strategy": "Vivid (BollBot x BollTop TF:60)", "upTime": "2023-05-07 03:49", "key": 8}, {"symbol": "TSLA", "barTime": "2023-05-06 02:30", "content": "SELL@170.16 Size:2 Gain:-5.80%", "strategy": "Revival (BUY:SMA30 SELL:BollTop TF:60)", "upTime": "2023-05-07 03:37", "key": 9}, {"symbol": "GOOGL", "barTime": "2023-05-06 02:30", "content": "BUY@104.65 Size:4", "strategy": "Revival (BUY:SMA30 SELL:BollTop TF:60)", "upTime": "2023-05-07 03:13", "key": 10}, {"symbol": "LRCX", "barTime": "2023-05-06 02:30", "content": "SELL@528.41 Size:1 Gain:5.90%", "strategy": "Vivid (BollBot x BollTop TF:60)", "upTime": "2023-05-07 03:49", "key": 11}, {"symbol": "NKE", "barTime": "2023-05-06 01:30", "content": "BUY@125.18 Size:3", "strategy": "Revival (BUY:SMA30 SELL:BollTop TF:60)", "upTime": "2023-05-07 03:13", "key": 12}, {"symbol": "LABU", "barTime": "2023-05-06 01:30", "content": "SELL@6.76 Size:62 Gain:12.73%", "strategy": "Vivid (BollBot x BollTop TF:60)", "upTime": "2023-05-07 03:30", "key": 13}, {"symbol": "UPRO", "barTime": "2023-05-06 00:30", "content": "BUY@38.15 Size:13", "strategy": "Revival (BUY:SMA30 SELL:BollTop TF:60)", "upTime": "2023-05-07 03:49", "key": 14}, {"symbol": "MNST", "barTime": "2023-05-06 00:30", "content": "SELL@59.78 Size:0 Gain:0.00%", "strategy": "Revival (BUY:SMA30 SELL:BollTop TF:60)", "upTime": "2023-05-07 03:49", "key": 15}, {"symbol": "NFLX", "barTime": "2023-05-06 00:30", "content": "BUY@319.18 Size:1", "strategy": "Revival (BUY:SMA30 SELL:BollTop TF:60)", "upTime": "2023-05-07 03:13", "key": 16}, {"symbol": "META", "barTime": "2023-05-06 00:30", "content": "BUY@230.92 Size:2", "strategy": "Vivid (BollBot x BollTop TF:60)", "upTime": "2023-05-07 03:49", "key": 17}, {"symbol": "MNST", "barTime": "2023-05-06 00:30", "content": "SELL@59.78 Size:0 Gain:0.00%", "strategy": "Vivid (BollBot x BollTop TF:60)", "upTime": "2023-05-07 03:30", "key": 18}, {"symbol": "AAPL", "barTime": "2023-05-05 23:30", "content": "SELL@173.26 Size:2 Gain:5.42%", "strategy": "Vivid (BollBot x BollTop TF:60)", "upTime": "2023-05-07 03:49", "key": 19}, {"symbol": "NVDA", "barTime": "2023-05-05 23:30", "content": "SELL@283.97 Size:1 Gain:3.81%", "strategy": "Vivid (BollBot x BollTop TF:60)", "upTime": "2023-05-07 03:49", "key": 20}, {"symbol": "AAPL", "barTime": "2023-05-05 23:30", "content": "SELL@173.26 Size:2 Gain:11.35%", "strategy": "Revival (BUY:SMA30 SELL:BollTop TF:60)", "upTime": "2023-05-07 03:49", "key": 21}, {"symbol": "MSFT", "barTime": "2023-05-05 23:30", "content": "SELL@308.82 Size:1 Gain:8.51%", "strategy": "Revival (BUY:SMA30 SELL:BollTop TF:60)", "upTime": "2023-05-07 03:13", "key": 22}, {"symbol": "MSFT", "barTime": "2023-05-05 23:30", "content": "SELL@308.82 Size:1 Gain:10.61%", "strategy": "Vivid (BollBot x BollTop TF:60)", "upTime": "2023-05-07 03:13", "key": 23}, {"symbol": "KO", "barTime": "2023-05-05 23:30", "content": "SELL@64.03 Size:0 Gain:0.00%", "strategy": "Vivid (BollBot x BollTop TF:60)", "upTime": "2023-05-07 03:30", "key": 24}, {"symbol": "SMH", "barTime": "2023-05-05 22:30", "content": "BUY@122.27 Size:4", "strategy": "Revival (BUY:SMA30 SELL:BollTop TF:60)", "upTime": "2023-05-07 03:30", "key": 25}, {"symbol": "SOXL", "barTime": "2023-05-05 22:30", "content": "BUY@13.99 Size:35", "strategy": "Revival (BUY:SMA30 SELL:BollTop TF:60)", "upTime": "2023-05-07 03:30", "key": 26}, {"symbol": "UPRO", "barTime": "2023-05-05 22:30", "content": "BUY@38.10 Size:13", "strategy": "Revival (BUY:SMA30 SELL:BollTop TF:60)", "upTime": "2023-05-07 03:49", "key": 27}, {"symbol": "SSO", "barTime": "2023-05-05 22:30", "content": "BUY@49.78 Size:10", "strategy": "Revival (BUY:SMA30 SELL:BollTop TF:60)", "upTime": "2023-05-07 03:13", "key": 28}, {"symbol": "TSLA", "barTime": "2023-05-05 21:30", "content": "BUY@165.20 Size:3", "strategy": "Revival (BUY:SMA30 SELL:BollTop TF:60)", "upTime": "2023-05-07 03:37", "key": 29}, {"symbol": "QQQ", "barTime": "2023-05-05 21:30", "content": "BUY@317.52 Size:1", "strategy": "Revival (BUY:SMA30 SELL:BollTop TF:60)", "upTime": "2023-05-07 03:13", "key": 30}, {"symbol": "AAPL", "barTime": "2023-05-05 21:30", "content": "BUY@171.63 Size:2", "strategy": "Revival (BUY:SMA30 SELL:BollTop TF:60)", "upTime": "2023-05-07 03:49", "key": 31}, {"symbol": "NVDA", "barTime": "2023-05-05 21:30", "content": "BUY@279.72 Size:1", "strategy": "Revival (BUY:SMA30 SELL:BollTop TF:60)", "upTime": "2023-05-07 03:30", "key": 32}, {"symbol": "MSFT", "barTime": "2023-05-05 21:30", "content": "BUY@305.19 Size:1", "strategy": "Revival (BUY:SMA30 SELL:BollTop TF:60)", "upTime": "2023-05-07 03:13", "key": 33}, {"symbol": "TQQQ", "barTime": "2023-05-05 21:30", "content": "BUY@27.41 Size:18", "strategy": "Revival (BUY:SMA30 SELL:BollTop TF:60)", "upTime": "2023-05-07 03:49", "key": 34}, {"symbol": "LRCX", "barTime": "2023-05-05 21:30", "content": "BUY@516.74 Size:0", "strategy": "Revival (BUY:SMA30 SELL:BollTop TF:60)", "upTime": "2023-05-07 03:49", "key": 35}, {"symbol": "NFLX", "barTime": "2023-05-05 21:30", "content": "BUY@319.10 Size:1", "strategy": "Revival (BUY:SMA30 SELL:BollTop TF:60)", "upTime": "2023-05-07 03:13", "key": 36}, {"symbol": "ASML", "barTime": "2023-05-05 21:30", "content": "BUY@636.79 Size:0", "strategy": "Revival (BUY:SMA30 SELL:BollTop TF:60)", "upTime": "2023-05-07 03:13", "key": 37}, {"symbol": "TCEHY", "barTime": "2023-05-05 21:30", "content": "BUY@43.04 Size:11", "strategy": "Revival (BUY:SMA30 SELL:BollTop TF:60)", "upTime": "2023-05-07 03:13", "key": 38}, {"symbol": "KO", "barTime": "2023-05-05 21:30", "content": "BUY@63.38 Size:7", "strategy": "Revival (BUY:SMA30 SELL:BollTop TF:60)", "upTime": "2023-05-07 03:49", "key": 39}, {"symbol": "ASML", "barTime": "2023-05-05 02:30", "content": "BUY@630.63 Size:0", "strategy": "Revival (BUY:SMA30 SELL:BollTop TF:60)", "upTime": "2023-05-07 03:13", "key": 40}, {"symbol": "NVDA", "barTime": "2023-05-05 01:30", "content": "BUY@271.51 Size:1", "strategy": "Vivid (BollBot x BollTop TF:60)", "upTime": "2023-05-07 03:49", "key": 41}, {"symbol": "NFLX", "barTime": "2023-05-05 00:30", "content": "BUY@319.08 Size:1", "strategy": "Revival (BUY:SMA30 SELL:BollTop TF:60)", "upTime": "2023-05-07 03:13", "key": 42}, {"symbol": "LRCX", "barTime": "2023-05-05 00:30", "content": "BUY@507.66 Size:0", "strategy": "Vivid (BollBot x BollTop TF:60)", "upTime": "2023-05-07 03:49", "key": 43}, {"symbol": "NKE", "barTime": "2023-05-05 00:30", "content": "BUY@122.60 Size:4", "strategy": "Vivid (BollBot x BollTop TF:60)", "upTime": "2023-05-07 03:13", "key": 44}, {"symbol": "AAPL", "barTime": "2023-05-04 23:30", "content": "BUY@164.55 Size:3", "strategy": "Vivid (BollBot x BollTop TF:60)", "upTime": "2023-05-07 03:49", "key": 45}, {"symbol": "ASML", "barTime": "2023-05-04 23:30", "content": "BUY@629.44 Size:0", "strategy": "Revival (BUY:SMA30 SELL:BollTop TF:60)", "upTime": "2023-05-07 03:13", "key": 46}, {"symbol": "SMH", "barTime": "2023-05-04 23:30", "content": "BUY@120.35 Size:4", "strategy": "Vivid (BollBot x BollTop TF:60)", "upTime": "2023-05-07 03:30", "key": 47}, {"symbol": "SOXL", "barTime": "2023-05-04 23:30", "content": "BUY@13.34 Size:37", "strategy": "Vivid (BollBot x BollTop TF:60)", "upTime": "2023-05-07 03:49", "key": 48}, {"symbol": "UPRO", "barTime": "2023-05-04 23:30", "content": "BUY@36.51 Size:13", "strategy": "Vivid (BollBot x BollTop TF:60)", "upTime": "2023-05-07 03:49", "key": 49}, {"symbol": "SSO", "barTime": "2023-05-04 23:30", "content": "BUY@48.39 Size:10", "strategy": "Vivid (BollBot x BollTop TF:60)", "upTime": "2023-05-07 03:13", "key": 50}, {"symbol": "NUGT", "barTime": "2023-05-04 23:30", "content": "SELL@50.66 Size:8 Gain:13.11%", "strategy": "Vivid (BollBot x BollTop TF:60)", "upTime": "2023-05-07 03:49", "key": 51}, {"symbol": "AMZN", "barTime": "2023-05-04 22:30", "content": "BUY@103.55 Size:4", "strategy": "Revival (BUY:SMA30 SELL:BollTop TF:60)", "upTime": "2023-05-07 03:49", "key": 52}, {"symbol": "QQQ", "barTime": "2023-05-04 22:30", "content": "BUY@313.60 Size:1", "strategy": "Vivid (BollBot x BollTop TF:60)", "upTime": "2023-05-07 03:13", "key": 53}, {"symbol": "NVDA", "barTime": "2023-05-04 22:30", "content": "BUY@273.54 Size:1", "strategy": "Vivid (BollBot x BollTop TF:60)", "upTime": "2023-05-07 03:49", "key": 54}, {"symbol": "MSFT", "barTime": "2023-05-04 22:30", "content": "BUY@302.95 Size:1", "strategy": "Revival (BUY:SMA30 SELL:BollTop TF:60)", "upTime": "2023-05-07 03:13", "key": 55}, {"symbol": "NUGT", "barTime": "2023-05-04 22:30", "content": "SELL@50.83 Size:8 Gain:11.70%", "strategy": "Revival (BUY:SMA30 SELL:BollTop TF:60)", "upTime": "2023-05-07 03:49", "key": 56}, {"symbol": "META", "barTime": "2023-05-04 22:30", "content": "BUY@235.21 Size:2", "strategy": "Vivid (BollBot x BollTop TF:60)", "upTime": "2023-05-07 03:49", "key": 57}, {"symbol": "MSFT", "barTime": "2023-05-04 22:30", "content": "BUY@302.95 Size:1", "strategy": "Vivid (BollBot x BollTop TF:60)", "upTime": "2023-05-07 03:13", "key": 58}, {"symbol": "GOOGL", "barTime": "2023-05-04 22:30", "content": "BUY@103.88 Size:4", "strategy": "Vivid (BollBot x BollTop TF:60)", "upTime": "2023-05-07 03:13", "key": 59}, {"symbol": "TQQQ", "barTime": "2023-05-04 22:30", "content": "BUY@26.44 Size:18", "strategy": "Vivid (BollBot x BollTop TF:60)", "upTime": "2023-05-07 03:49", "key": 60}, {"symbol": "META", "barTime": "2023-05-04 03:30", "content": "BUY@234.66 Size:2", "strategy": "Vivid (BollBot x BollTop TF:60)", "upTime": "2023-05-07 03:49", "key": 61}, {"symbol": "LRCX", "barTime": "2023-05-04 03:30", "content": "BUY@509.40 Size:0", "strategy": "Vivid (BollBot x BollTop TF:60)", "upTime": "2023-05-07 03:49", "key": 62}, {"symbol": "AMZN", "barTime": "2023-05-04 02:30", "content": "SELL@103.67 Size:4 Gain:0.60%", "strategy": "Vivid (BollBot x BollTop TF:60)", "upTime": "2023-05-07 03:49", "key": 63}, {"symbol": "MNST", "barTime": "2023-05-04 02:30", "content": "SELL@58.43 Size:0 Gain:0.00%", "strategy": "Revival (BUY:SMA30 SELL:BollTop TF:60)", "upTime": "2023-05-07 03:49", "key": 64}, {"symbol": "ASML", "barTime": "2023-05-04 02:30", "content": "SELL@635.03 Size:0 Gain:0.00%", "strategy": "Revival (BUY:SMA30 SELL:BollTop TF:60)", "upTime": "2023-05-07 03:13", "key": 65}, {"symbol": "MSFT", "barTime": "2023-05-04 02:30", "content": "SELL@304.66 Size:1 Gain:9.12%", "strategy": "Vivid (BollBot x BollTop TF:60)", "upTime": "2023-05-07 03:13", "key": 66}, {"symbol": "LABU", "barTime": "2023-05-04 02:30", "content": "SELL@6.22 Size:67 Gain:3.73%", "strategy": "Vivid (BollBot x BollTop TF:60)", "upTime": "2023-05-07 03:30", "key": 67}, {"symbol": "MNST", "barTime": "2023-05-04 02:30", "content": "SELL@58.43 Size:0 Gain:0.00%", "strategy": "Vivid (BollBot x BollTop TF:60)", "upTime": "2023-05-07 03:30", "key": 68}, {"symbol": "ASML", "barTime": "2023-05-04 02:30", "content": "SELL@635.03 Size:0 Gain:0.00%", "strategy": "Vivid (BollBot x BollTop TF:60)", "upTime": "2023-05-07 03:13", "key": 69}, {"symbol": "QQQ", "barTime": "2023-05-04 01:30", "content": "BUY@318.12 Size:1", "strategy": "Revival (BUY:SMA30 SELL:BollTop TF:60)", "upTime": "2023-05-07 03:13", "key": 70}, {"symbol": "NVDA", "barTime": "2023-05-04 01:30", "content": "BUY@279.96 Size:1", "strategy": "Revival (BUY:SMA30 SELL:BollTop TF:60)", "upTime": "2023-05-07 03:30", "key": 71}, {"symbol": "AMZN", "barTime": "2023-05-04 01:30", "content": "BUY@104.40 Size:4", "strategy": "Revival (BUY:SMA30 SELL:BollTop TF:60)", "upTime": "2023-05-07 03:49", "key": 72}, {"symbol": "TSLA", "barTime": "2023-05-04 01:30", "content": "SELL@164.60 Size:2 Gain:-1.47%", "strategy": "Vivid (BollBot x BollTop TF:60)", "upTime": "2023-05-07 03:49", "key": 73}, {"symbol": "GOOGL", "barTime": "2023-05-04 01:30", "content": "BUY@105.74 Size:4", "strategy": "Revival (BUY:SMA30 SELL:BollTop TF:60)", "upTime": "2023-05-07 03:13", "key": 74}, {"symbol": "SMH", "barTime": "2023-05-04 01:30", "content": "BUY@122.60 Size:4", "strategy": "Revival (BUY:SMA30 SELL:BollTop TF:60)", "upTime": "2023-05-07 03:30", "key": 75}, {"symbol": "TQQQ", "barTime": "2023-05-04 01:30", "content": "BUY@27.63 Size:18", "strategy": "Revival (BUY:SMA30 SELL:BollTop TF:60)", "upTime": "2023-05-07 03:49", "key": 76}, {"symbol": "LRCX", "barTime": "2023-05-04 01:30", "content": "BUY@516.94 Size:0", "strategy": "Revival (BUY:SMA30 SELL:BollTop TF:60)", "upTime": "2023-05-07 03:49", "key": 77}, {"symbol": "SOXL", "barTime": "2023-05-04 00:30", "content": "BUY@14.04 Size:35", "strategy": "Revival (BUY:SMA30 SELL:BollTop TF:60)", "upTime": "2023-05-07 03:30", "key": 78}, {"symbol": "NFLX", "barTime": "2023-05-04 00:30", "content": "BUY@320.99 Size:1", "strategy": "Revival (BUY:SMA30 SELL:BollTop TF:60)", "upTime": "2023-05-07 03:13", "key": 79}, {"symbol": "NKE", "barTime": "2023-05-04 00:30", "content": "BUY@125.95 Size:3", "strategy": "Revival (BUY:SMA30 SELL:BollTop TF:60)", "upTime": "2023-05-07 03:13", "key": 80}, {"symbol": "LRCX", "barTime": "2023-05-04 00:30", "content": "BUY@514.53 Size:0", "strategy": "Vivid (BollBot x BollTop TF:60)", "upTime": "2023-05-07 03:49", "key": 81}, {"symbol": "SMH", "barTime": "2023-05-03 23:30", "content": "BUY@121.44 Size:4", "strategy": "Vivid (BollBot x BollTop TF:60)", "upTime": "2023-05-07 03:30", "key": 82}, {"symbol": "SOXL", "barTime": "2023-05-03 23:30", "content": "BUY@13.88 Size:36", "strategy": "Vivid (BollBot x BollTop TF:60)", "upTime": "2023-05-07 03:49", "key": 83}, {"symbol": "NUGT", "barTime": "2023-05-03 23:30", "content": "SELL@48.02 Size:9 Gain:7.22%", "strategy": "Vivid (BollBot x BollTop TF:60)", "upTime": "2023-05-07 03:49", "key": 84}, {"symbol": "MSFT", "barTime": "2023-05-03 22:30", "content": "BUY@303.30 Size:1", "strategy": "Revival (BUY:SMA30 SELL:BollTop TF:60)", "upTime": "2023-05-07 03:13", "key": 85}, {"symbol": "MNST", "barTime": "2023-05-03 22:30", "content": "SELL@57.77 Size:0 Gain:0.00%", "strategy": "Revival (BUY:SMA30 SELL:BollTop TF:60)", "upTime": "2023-05-07 03:49", "key": 86}, {"symbol": "MSFT", "barTime": "2023-05-03 22:30", "content": "BUY@303.30 Size:1", "strategy": "Vivid (BollBot x BollTop TF:60)", "upTime": "2023-05-07 03:13", "key": 87}, {"symbol": "MNST", "barTime": "2023-05-03 22:30", "content": "SELL@57.77 Size:0 Gain:0.00%", "strategy": "Vivid (BollBot x BollTop TF:60)", "upTime": "2023-05-07 03:30", "key": 88}, {"symbol": "NKE", "barTime": "2023-05-03 22:30", "content": "BUY@124.92 Size:4", "strategy": "Vivid (BollBot x BollTop TF:60)", "upTime": "2023-05-07 03:13", "key": 89}, {"symbol": "TSLA", "barTime": "2023-05-03 21:30", "content": "BUY@162.29 Size:3", "strategy": "Revival (BUY:SMA30 SELL:BollTop TF:60)", "upTime": "2023-05-07 03:37", "key": 90}, {"symbol": "LABU", "barTime": "2023-05-03 21:30", "content": "BUY@5.92 Size:84", "strategy": "Revival (BUY:SMA30 SELL:BollTop TF:60)", "upTime": "2023-05-07 03:49", "key": 91}, {"symbol": "NUGT", "barTime": "2023-05-03 21:30", "content": "SELL@47.55 Size:9 Gain:6.17%", "strategy": "Vivid (BollBot x BollTop TF:60)", "upTime": "2023-05-07 03:49", "key": 92}, {"symbol": "MNST", "barTime": "2023-05-03 03:30", "content": "SELL@57.54 Size:0 Gain:0.00%", "strategy": "Vivid (BollBot x BollTop TF:60)", "upTime": "2023-05-07 03:30", "key": 93}, {"symbol": "QQQ", "barTime": "2023-05-03 02:30", "content": "BUY@316.57 Size:1", "strategy": "Revival (BUY:SMA30 SELL:BollTop TF:60)", "upTime": "2023-05-07 03:13", "key": 94}, {"symbol": "NUGT", "barTime": "2023-05-03 02:30", "content": "SELL@47.48 Size:9 Gain:4.35%", "strategy": "Revival (BUY:SMA30 SELL:BollTop TF:60)", "upTime": "2023-05-07 03:49", "key": 95}, {"symbol": "KO", "barTime": "2023-05-03 02:30", "content": "BUY@63.40 Size:7", "strategy": "Revival (BUY:SMA30 SELL:BollTop TF:60)", "upTime": "2023-05-07 03:49", "key": 96}, {"symbol": "QQQ", "barTime": "2023-05-03 00:30", "content": "BUY@316.25 Size:1", "strategy": "Revival (BUY:SMA30 SELL:BollTop TF:60)", "upTime": "2023-05-07 03:13", "key": 97}, {"symbol": "QQQ", "barTime": "2023-05-03 00:30", "content": "BUY@316.25 Size:1", "strategy": "Vivid (BollBot x BollTop TF:60)", "upTime": "2023-05-07 03:13", "key": 98}, {"symbol": "TQQQ", "barTime": "2023-05-03 00:30", "content": "BUY@27.17 Size:18", "strategy": "Vivid (BollBot x BollTop TF:60)", "upTime": "2023-05-07 03:49", "key": 99}, {"symbol": "UPRO", "barTime": "2023-05-03 00:30", "content": "BUY@37.91 Size:13", "strategy": "Vivid (BollBot x BollTop TF:60)", "upTime": "2023-05-07 03:49", "key": 100}, {"symbol": "SSO", "barTime": "2023-05-03 00:30", "content": "BUY@49.59 Size:10", "strategy": "Vivid (BollBot x BollTop TF:60)", "upTime": "2023-05-07 03:13", "key": 101}, {"symbol": "TCEHY", "barTime": "2023-05-03 00:30", "content": "BUY@42.87 Size:11", "strategy": "Vivid (BollBot x BollTop TF:60)", "upTime": "2023-05-07 03:13", "key": 102}, {"symbol": "EDU", "barTime": "2023-05-03 00:30", "content": "BUY@41.42 Size:12", "strategy": "Vivid (BollBot x BollTop TF:60)", "upTime": "2023-05-07 03:49", "key": 103}, {"symbol": "AAPL", "barTime": "2023-05-02 23:30", "content": "BUY@166.43 Size:3", "strategy": "Vivid (BollBot x BollTop TF:60)", "upTime": "2023-05-07 03:49", "key": 104}, {"symbol": "NKE", "barTime": "2023-05-02 23:30", "content": "BUY@125.58 Size:3", "strategy": "Revival (BUY:SMA30 SELL:BollTop TF:60)", "upTime": "2023-05-07 03:13", "key": 105}, {"symbol": "GOOGL", "barTime": "2023-05-02 23:30", "content": "BUY@104.16 Size:4", "strategy": "Vivid (BollBot x BollTop TF:60)", "upTime": "2023-05-07 03:13", "key": 106}, {"symbol": "NFLX", "barTime": "2023-05-02 23:30", "content": "BUY@315.87 Size:1", "strategy": "Vivid (BollBot x BollTop TF:60)", "upTime": "2023-05-07 03:13", "key": 107}, {"symbol": "KO", "barTime": "2023-05-02 23:30", "content": "BUY@63.02 Size:7", "strategy": "Vivid (BollBot x BollTop TF:60)", "upTime": "2023-05-07 03:30", "key": 108}, {"symbol": "META", "barTime": "2023-05-02 21:30", "content": "SELL@241.34 Size:2 Gain:2.15%", "strategy": "Revival (BUY:SMA30 SELL:BollTop TF:60)", "upTime": "2023-05-07 03:49", "key": 109}, {"symbol": "NUGT", "barTime": "2023-05-02 21:30", "content": "BUY@45.19 Size:11", "strategy": "Revival (BUY:SMA30 SELL:BollTop TF:60)", "upTime": "2023-05-07 03:49", "key": 110}, {"symbol": "META", "barTime": "2023-05-02 21:30", "content": "SELL@241.34 Size:2 Gain:14.06%", "strategy": "Vivid (BollBot x BollTop TF:60)", "upTime": "2023-05-07 03:49", "key": 111}, {"symbol": "NUGT", "barTime": "2023-05-02 21:30", "content": "BUY@45.19 Size:11", "strategy": "Vivid (BollBot x BollTop TF:60)", "upTime": "2023-05-07 03:49", "key": 112}, {"symbol": "NVDA", "barTime": "2023-05-02 02:30", "content": "SELL@289.11 Size:1 Gain:8.29%", "strategy": "Vivid (BollBot x BollTop TF:60)", "upTime": "2023-05-07 03:49", "key": 113}, {"symbol": "NVDA", "barTime": "2023-05-02 01:30", "content": "SELL@288.79 Size:1 Gain:7.25%", "strategy": "Revival (BUY:SMA30 SELL:BollTop TF:60)", "upTime": "2023-05-07 03:30", "key": 114}, {"symbol": "LABU", "barTime": "2023-05-02 01:30", "content": "SELL@5.99 Size:70 Gain:2.91%", "strategy": "Revival (BUY:SMA30 SELL:BollTop TF:60)", "upTime": "2023-05-07 03:49", "key": 115}, {"symbol": "NUGT", "barTime": "2023-05-02 01:30", "content": "BUY@44.55 Size:11", "strategy": "Revival (BUY:SMA30 SELL:BollTop TF:60)", "upTime": "2023-05-07 03:49", "key": 116}, {"symbol": "LABU", "barTime": "2023-05-02 01:30", "content": "SELL@5.99 Size:70 Gain:-0.11%", "strategy": "Vivid (BollBot x BollTop TF:60)", "upTime": "2023-05-07 03:30", "key": 117}, {"symbol": "MNST", "barTime": "2023-05-02 01:30", "content": "SELL@56.80 Size:0 Gain:0.00%", "strategy": "Vivid (BollBot x BollTop TF:60)", "upTime": "2023-05-07 03:30", "key": 118}, {"symbol": "KO", "barTime": "2023-05-02 01:30", "content": "SELL@64.62 Size:1 Gain:2.08%", "strategy": "Vivid (BollBot x BollTop TF:60)", "upTime": "2023-05-07 03:30", "key": 119}, {"symbol": "KO", "barTime": "2023-05-02 00:30", "content": "SELL@64.64 Size:6 Gain:5.57%", "strategy": "Revival (BUY:SMA30 SELL:BollTop TF:60)", "upTime": "2023-05-07 03:49", "key": 120}, {"symbol": "SOXL", "barTime": "2023-05-02 00:30", "content": "SELL@14.65 Size:28 Gain:-2.79%", "strategy": "Vivid (BollBot x BollTop TF:60)", "upTime": "2023-05-07 03:49", "key": 121}, {"symbol": "TSLA", "barTime": "2023-05-01 23:30", "content": "BUY@159.35 Size:3", "strategy": "Revival (BUY:SMA30 SELL:BollTop TF:60)", "upTime": "2023-05-07 03:37", "key": 122}, {"symbol": "AMZN", "barTime": "2023-05-01 23:30", "content": "BUY@101.81 Size:4", "strategy": "Vivid (BollBot x BollTop TF:60)", "upTime": "2023-05-07 03:49", "key": 123}, {"symbol": "MNST", "barTime": "2023-05-01 23:30", "content": "SELL@56.82 Size:0 Gain:0.00%", "strategy": "Revival (BUY:SMA30 SELL:BollTop TF:60)", "upTime": "2023-05-07 03:49", "key": 124}, {"symbol": "NFLX", "barTime": "2023-05-01 23:30", "content": "BUY@319.02 Size:1", "strategy": "Vivid (BollBot x BollTop TF:60)", "upTime": "2023-05-07 03:13", "key": 125}, {"symbol": "NKE", "barTime": "2023-05-01 22:30", "content": "SELL@127.78 Size:3 Gain:4.41%", "strategy": "Revival (BUY:SMA30 SELL:BollTop TF:60)", "upTime": "2023-05-07 03:13", "key": 126}, {"symbol": "SOXL", "barTime": "2023-05-01 22:30", "content": "SELL@14.43 Size:29 Gain:-4.25%", "strategy": "Vivid (BollBot x BollTop TF:60)", "upTime": "2023-05-07 03:49", "key": 127}, {"symbol": "NKE", "barTime": "2023-05-01 22:30", "content": "SELL@127.78 Size:3 Gain:3.26%", "strategy": "Vivid (BollBot x BollTop TF:60)", "upTime": "2023-05-07 03:13", "key": 128}, {"symbol": "NUGT", "barTime": "2023-05-01 21:30", "content": "BUY@44.75 Size:11", "strategy": "Revival (BUY:SMA30 SELL:BollTop TF:60)", "upTime": "2023-05-07 03:49", "key": 129}, {"symbol": "SOXL", "barTime": "2023-04-29 03:30", "content": "SELL@14.23 Size:29 Gain:-5.58%", "strategy": "Vivid (BollBot x BollTop TF:60)", "upTime": "2023-05-07 03:49", "key": 130}, {"symbol": "LABU", "barTime": "2023-04-29 02:30", "content": "SELL@5.56 Size:75 Gain:-7.28%", "strategy": "Vivid (BollBot x BollTop TF:60)", "upTime": "2023-05-07 03:30", "key": 131}, {"symbol": "TSLA", "barTime": "2023-04-29 01:30", "content": "SELL@164.26 Size:2 Gain:-1.67%", "strategy": "Vivid (BollBot x BollTop TF:60)", "upTime": "2023-05-07 03:49", "key": 132}, {"symbol": "NVDA", "barTime": "2023-04-29 01:30", "content": "SELL@275.56 Size:2 Gain:3.21%", "strategy": "Vivid (BollBot x BollTop TF:60)", "upTime": "2023-05-07 03:49", "key": 133}, {"symbol": "SMH", "barTime": "2023-04-29 01:30", "content": "SELL@123.14 Size:3 Gain:-0.71%", "strategy": "Revival (BUY:SMA30 SELL:BollTop TF:60)", "upTime": "2023-05-07 03:30", "key": 134}, {"symbol": "SOXL", "barTime": "2023-04-29 01:30", "content": "SELL@14.07 Size:30 Gain:-10.81%", "strategy": "Revival (BUY:SMA30 SELL:BollTop TF:60)", "upTime": "2023-05-07 03:30", "key": 135}, {"symbol": "LABU", "barTime": "2023-04-29 01:30", "content": "SELL@5.62 Size:74 Gain:-3.45%", "strategy": "Revival (BUY:SMA30 SELL:BollTop TF:60)", "upTime": "2023-05-07 03:49", "key": 136}, {"symbol": "SMH", "barTime": "2023-04-29 01:30", "content": "SELL@123.14 Size:3 Gain:-0.21%", "strategy": "Vivid (BollBot x BollTop TF:60)", "upTime": "2023-05-07 03:30", "key": 137}, {"symbol": "SOXL", "barTime": "2023-04-29 01:30", "content": "SELL@14.07 Size:30 Gain:-6.64%", "strategy": "Vivid (BollBot x BollTop TF:60)", "upTime": "2023-05-07 03:49", "key": 138}, {"symbol": "MNST", "barTime": "2023-04-29 01:30", "content": "SELL@55.64 Size:0 Gain:0.00%", "strategy": "Vivid (BollBot x BollTop TF:60)", "upTime": "2023-05-07 03:30", "key": 139}, {"symbol": "KO", "barTime": "2023-04-29 01:30", "content": "SELL@63.78 Size:6 Gain:0.74%", "strategy": "Vivid (BollBot x BollTop TF:60)", "upTime": "2023-05-07 03:30", "key": 140}, {"symbol": "MNST", "barTime": "2023-04-29 00:30", "content": "SELL@55.89 Size:0 Gain:0.00%", "strategy": "Revival (BUY:SMA30 SELL:BollTop TF:60)", "upTime": "2023-05-07 03:49", "key": 141}, {"symbol": "KO", "barTime": "2023-04-29 00:30", "content": "SELL@63.92 Size:6 Gain:4.39%", "strategy": "Revival (BUY:SMA30 SELL:BollTop TF:60)", "upTime": "2023-05-07 03:49", "key": 142}, {"symbol": "UPRO", "barTime": "2023-04-29 00:30", "content": "SELL@39.82 Size:10 Gain:4.33%", "strategy": "Vivid (BollBot x BollTop TF:60)", "upTime": "2023-05-07 03:49", "key": 143}, {"symbol": "SSO", "barTime": "2023-04-29 00:30", "content": "SELL@51.39 Size:8 Gain:3.29%", "strategy": "Vivid (BollBot x BollTop TF:60)", "upTime": "2023-05-07 03:13", "key": 144}, {"symbol": "GOOGL", "barTime": "2023-04-28 23:30", "content": "BUY@105.44 Size:4", "strategy": "Revival (BUY:SMA30 SELL:BollTop TF:60)", "upTime": "2023-05-07 03:13", "key": 145}, {"symbol": "SOXL", "barTime": "2023-04-28 23:30", "content": "BUY@13.74 Size:36", "strategy": "Revival (BUY:SMA30 SELL:BollTop TF:60)", "upTime": "2023-05-07 03:30", "key": 146}, {"symbol": "LABU", "barTime": "2023-04-28 23:30", "content": "BUY@5.50 Size:90", "strategy": "Revival (BUY:SMA30 SELL:BollTop TF:60)", "upTime": "2023-05-07 03:49", "key": 147}, {"symbol": "AAPL", "barTime": "2023-04-28 22:30", "content": "SELL@168.29 Size:2 Gain:8.16%", "strategy": "Revival (BUY:SMA30 SELL:BollTop TF:60)", "upTime": "2023-05-07 03:49", "key": 148}, {"symbol": "AAPL", "barTime": "2023-04-28 22:30", "content": "SELL@168.29 Size:2 Gain:2.61%", "strategy": "Vivid (BollBot x BollTop TF:60)", "upTime": "2023-05-07 03:49", "key": 149}, {"symbol": "SMH", "barTime": "2023-04-28 22:30", "content": "SELL@122.23 Size:3 Gain:-1.44%", "strategy": "Revival (BUY:SMA30 SELL:BollTop TF:60)", "upTime": "2023-05-07 03:30", "key": 150}, {"symbol": "SOXL", "barTime": "2023-04-28 22:30", "content": "SELL@13.73 Size:30 Gain:-12.97%", "strategy": "Revival (BUY:SMA30 SELL:BollTop TF:60)", "upTime": "2023-05-07 03:30", "key": 151}, {"symbol": "UPRO", "barTime": "2023-04-28 22:30", "content": "SELL@39.33 Size:11 Gain:5.89%", "strategy": "Revival (BUY:SMA30 SELL:BollTop TF:60)", "upTime": "2023-05-07 03:49", "key": 152}, {"symbol": "SSO", "barTime": "2023-04-28 22:30", "content": "SELL@50.97 Size:8 Gain:4.80%", "strategy": "Revival (BUY:SMA30 SELL:BollTop TF:60)", "upTime": "2023-05-07 03:13", "key": 153}, {"symbol": "MNST", "barTime": "2023-04-28 22:30", "content": "SELL@55.54 Size:0 Gain:0.00%", "strategy": "Revival (BUY:SMA30 SELL:BollTop TF:60)", "upTime": "2023-05-07 03:49", "key": 154}, {"symbol": "LRCX", "barTime": "2023-04-28 22:30", "content": "SELL@514.62 Size:1 Gain:5.10%", "strategy": "Revival (BUY:SMA30 SELL:BollTop TF:60)", "upTime": "2023-05-07 03:49", "key": 155}, {"symbol": "NFLX", "barTime": "2023-04-28 22:30", "content": "SELL@328.44 Size:1 Gain:0.48%", "strategy": "Revival (BUY:SMA30 SELL:BollTop TF:60)", "upTime": "2023-05-07 03:13", "key": 156}, {"symbol": "NUGT", "barTime": "2023-04-28 22:30", "content": "BUY@44.84 Size:11", "strategy": "Revival (BUY:SMA30 SELL:BollTop TF:60)", "upTime": "2023-05-07 03:49", "key": 157}, {"symbol": "ASML", "barTime": "2023-04-28 22:30", "content": "SELL@634.06 Size:0 Gain:0.00%", "strategy": "Revival (BUY:SMA30 SELL:BollTop TF:60)", "upTime": "2023-05-07 03:13", "key": 158}, {"symbol": "NKE", "barTime": "2023-04-28 22:30", "content": "SELL@126.01 Size:3 Gain:2.96%", "strategy": "Revival (BUY:SMA30 SELL:BollTop TF:60)", "upTime": "2023-05-07 03:13", "key": 159}, {"symbol": "SMH", "barTime": "2023-04-28 22:30", "content": "SELL@122.23 Size:3 Gain:-0.94%", "strategy": "Vivid (BollBot x BollTop TF:60)", "upTime": "2023-05-07 03:30", "key": 160}, {"symbol": "SOXL", "barTime": "2023-04-28 22:30", "content": "SELL@13.73 Size:30 Gain:-8.90%", "strategy": "Vivid (BollBot x BollTop TF:60)", "upTime": "2023-05-07 03:49", "key": 161}, {"symbol": "TQQQ", "barTime": "2023-04-28 22:30", "content": "SELL@27.59 Size:15 Gain:6.77%", "strategy": "Vivid (BollBot x BollTop TF:60)", "upTime": "2023-05-07 03:49", "key": 162}, {"symbol": "UPRO", "barTime": "2023-04-28 22:30", "content": "SELL@39.33 Size:11 Gain:3.06%", "strategy": "Vivid (BollBot x BollTop TF:60)", "upTime": "2023-05-07 03:49", "key": 163}, {"symbol": "SSO", "barTime": "2023-04-28 22:30", "content": "SELL@50.97 Size:8 Gain:2.44%", "strategy": "Vivid (BollBot x BollTop TF:60)", "upTime": "2023-05-07 03:13", "key": 164}, {"symbol": "LRCX", "barTime": "2023-04-28 22:30", "content": "SELL@514.62 Size:1 Gain:3.13%", "strategy": "Vivid (BollBot x BollTop TF:60)", "upTime": "2023-05-07 03:49", "key": 165}, {"symbol": "NFLX", "barTime": "2023-04-28 22:30", "content": "SELL@328.44 Size:1 Gain:1.56%", "strategy": "Vivid (BollBot x BollTop TF:60)", "upTime": "2023-05-07 03:13", "key": 166}, {"symbol": "ASML", "barTime": "2023-04-28 22:30", "content": "SELL@634.06 Size:0 Gain:0.00%", "strategy": "Vivid (BollBot x BollTop TF:60)", "upTime": "2023-05-07 03:13", "key": 167}, {"symbol": "NKE", "barTime": "2023-04-28 22:30", "content": "SELL@126.01 Size:3 Gain:1.83%", "strategy": "Vivid (BollBot x BollTop TF:60)", "upTime": "2023-05-07 03:13", "key": 168}, {"symbol": "SOXL", "barTime": "2023-04-28 21:30", "content": "BUY@13.80 Size:36", "strategy": "Revival (BUY:SMA30 SELL:BollTop TF:60)", "upTime": "2023-05-07 03:30", "key": 169}, {"symbol": "KO", "barTime": "2023-04-28 21:30", "content": "BUY@63.09 Size:7", "strategy": "Revival (BUY:SMA30 SELL:BollTop TF:60)", "upTime": "2023-05-07 03:49", "key": 170}, {"symbol": "TSLA", "barTime": "2023-04-28 03:30", "content": "BUY@158.59 Size:3", "strategy": "Revival (BUY:SMA30 SELL:BollTop TF:60)", "upTime": "2023-05-07 03:37", "key": 171}, {"symbol": "AAPL", "barTime": "2023-04-28 03:30", "content": "SELL@168.41 Size:2 Gain:8.24%", "strategy": "Revival (BUY:SMA30 SELL:BollTop TF:60)", "upTime": "2023-05-07 03:49", "key": 172}, {"symbol": "QQQ", "barTime": "2023-04-28 03:30", "content": "SELL@320.35 Size:1 Gain:2.31%", "strategy": "Vivid (BollBot x BollTop TF:60)", "upTime": "2023-05-07 03:13", "key": 173}, {"symbol": "SMH", "barTime": "2023-04-28 03:30", "content": "BUY@120.37 Size:4", "strategy": "Revival (BUY:SMA30 SELL:BollTop TF:60)", "upTime": "2023-05-07 03:30", "key": 174}, {"symbol": "UPRO", "barTime": "2023-04-28 03:30", "content": "SELL@38.94 Size:11 Gain:4.84%", "strategy": "Revival (BUY:SMA30 SELL:BollTop TF:60)", "upTime": "2023-05-07 03:49", "key": 175}, {"symbol": "SSO", "barTime": "2023-04-28 03:30", "content": "SELL@50.66 Size:8 Gain:4.16%", "strategy": "Revival (BUY:SMA30 SELL:BollTop TF:60)", "upTime": "2023-05-07 03:13", "key": 176}, {"symbol": "MNST", "barTime": "2023-04-28 03:30", "content": "SELL@55.28 Size:5 Gain:8.52%", "strategy": "Revival (BUY:SMA30 SELL:BollTop TF:60)", "upTime": "2023-05-07 03:49", "key": 177}, {"symbol": "TQQQ", "barTime": "2023-04-28 03:30", "content": "SELL@27.69 Size:15 Gain:7.16%", "strategy": "Vivid (BollBot x BollTop TF:60)", "upTime": "2023-05-07 03:49", "key": 178}, {"symbol": "QQQ", "barTime": "2023-04-28 02:30", "content": "SELL@320.57 Size:1 Gain:2.63%", "strategy": "Revival (BUY:SMA30 SELL:BollTop TF:60)", "upTime": "2023-05-07 03:13", "key": 179}, {"symbol": "AMZN", "barTime": "2023-04-28 02:30", "content": "SELL@109.73 Size:0 Gain:0.00%", "strategy": "Vivid (BollBot x BollTop TF:60)", "upTime": "2023-05-07 03:49", "key": 180}, {"symbol": "TQQQ", "barTime": "2023-04-28 02:30", "content": "SELL@27.76 Size:15 Gain:7.20%", "strategy": "Revival (BUY:SMA30 SELL:BollTop TF:60)", "upTime": "2023-05-07 03:49", "key": 181}, {"symbol": "GOOGL", "barTime": "2023-04-28 02:30", "content": "SELL@108.22 Size:4 Gain:3.78%", "strategy": "Vivid (BollBot x BollTop TF:60)", "upTime": "2023-05-07 03:13", "key": 182}, {"symbol": "AAPL", "barTime": "2023-04-28 01:30", "content": "SELL@167.45 Size:2 Gain:7.62%", "strategy": "Revival (BUY:SMA30 SELL:BollTop TF:60)", "upTime": "2023-05-07 03:49", "key": 183}, {"symbol": "META", "barTime": "2023-04-28 01:30", "content": "SELL@240.33 Size:2 Gain:14.08%", "strategy": "Revival (BUY:SMA30 SELL:BollTop TF:60)", "upTime": "2023-05-07 03:49", "key": 184}, {"symbol": "GOOGL", "barTime": "2023-04-28 01:30", "content": "SELL@108.17 Size:4 Gain:3.47%", "strategy": "Revival (BUY:SMA30 SELL:BollTop TF:60)", "upTime": "2023-05-07 03:13", "key": 185}, {"symbol": "NKE", "barTime": "2023-04-28 01:30", "content": "BUY@124.26 Size:4", "strategy": "Revival (BUY:SMA30 SELL:BollTop TF:60)", "upTime": "2023-05-07 03:13", "key": 186}, {"symbol": "META", "barTime": "2023-04-28 01:30", "content": "SELL@240.33 Size:2 Gain:13.58%", "strategy": "Vivid (BollBot x BollTop TF:60)", "upTime": "2023-05-07 03:49", "key": 187}, {"symbol": "NFLX", "barTime": "2023-04-28 01:30", "content": "SELL@325.94 Size:1 Gain:0.78%", "strategy": "Vivid (BollBot x BollTop TF:60)", "upTime": "2023-05-07 03:13", "key": 188}, {"symbol": "NVDA", "barTime": "2023-04-28 00:30", "content": "BUY@267.65 Size:1", "strategy": "Revival (BUY:SMA30 SELL:BollTop TF:60)", "upTime": "2023-05-07 03:30", "key": 189}, {"symbol": "AMZN", "barTime": "2023-04-28 00:30", "content": "SELL@110.12 Size:4 Gain:14.57%", "strategy": "Revival (BUY:SMA30 SELL:BollTop TF:60)", "upTime": "2023-05-07 03:49", "key": 190}, {"symbol": "UPRO", "barTime": "2023-04-28 00:30", "content": "BUY@37.95 Size:13", "strategy": "Revival (BUY:SMA30 SELL:BollTop TF:60)", "upTime": "2023-05-07 03:49", "key": 191}, {"symbol": "LRCX", "barTime": "2023-04-28 00:30", "content": "BUY@505.24 Size:0", "strategy": "Revival (BUY:SMA30 SELL:BollTop TF:60)", "upTime": "2023-05-07 03:49", "key": 192}, {"symbol": "NUGT", "barTime": "2023-04-28 00:30", "content": "BUY@44.66 Size:11", "strategy": "Revival (BUY:SMA30 SELL:BollTop TF:60)", "upTime": "2023-05-07 03:49", "key": 193}, {"symbol": "TQQQ", "barTime": "2023-04-27 23:30", "content": "SELL@27.24 Size:15 Gain:5.20%", "strategy": "Revival (BUY:SMA30 SELL:BollTop TF:60)", "upTime": "2023-05-07 03:49", "key": 194}, {"symbol": "SSO", "barTime": "2023-04-27 23:30", "content": "BUY@49.47 Size:10", "strategy": "Revival (BUY:SMA30 SELL:BollTop TF:60)", "upTime": "2023-05-07 03:13", "key": 195}, {"symbol": "NFLX", "barTime": "2023-04-27 23:30", "content": "BUY@323.58 Size:1", "strategy": "Revival (BUY:SMA30 SELL:BollTop TF:60)", "upTime": "2023-05-07 03:13", "key": 196}, {"symbol": "KO", "barTime": "2023-04-27 23:30", "content": "BUY@62.70 Size:7", "strategy": "Vivid (BollBot x BollTop TF:60)", "upTime": "2023-05-07 03:30", "key": 197}, {"symbol": "NUGT", "barTime": "2023-04-27 22:30", "content": "BUY@44.46 Size:11", "strategy": "Revival (BUY:SMA30 SELL:BollTop TF:60)", "upTime": "2023-05-07 03:49", "key": 198}, {"symbol": "ASML", "barTime": "2023-04-27 22:30", "content": "BUY@615.91 Size:0", "strategy": "Revival (BUY:SMA30 SELL:BollTop TF:60)", "upTime": "2023-05-07 03:13", "key": 199}, {"symbol": "LABU", "barTime": "2023-04-27 22:30", "content": "BUY@5.23 Size:95", "strategy": "Vivid (BollBot x BollTop TF:60)", "upTime": "2023-05-07 03:30", "key": 200}, {"symbol": "MNST", "barTime": "2023-04-27 22:30", "content": "SELL@54.58 Size:0 Gain:0.00%", "strategy": "Vivid (BollBot x BollTop TF:60)", "upTime": "2023-05-07 03:30", "key": 201}, {"symbol": "QQQ", "barTime": "2023-04-27 21:30", "content": "BUY@313.49 Size:1", "strategy": "Revival (BUY:SMA30 SELL:BollTop TF:60)", "upTime": "2023-05-07 03:13", "key": 202}, {"symbol": "AAPL", "barTime": "2023-04-27 21:30", "content": "BUY@164.59 Size:3", "strategy": "Revival (BUY:SMA30 SELL:BollTop TF:60)", "upTime": "2023-05-07 03:49", "key": 203}, {"symbol": "AMZN", "barTime": "2023-04-27 21:30", "content": "BUY@107.51 Size:4", "strategy": "Revival (BUY:SMA30 SELL:BollTop TF:60)", "upTime": "2023-05-07 03:49", "key": 204}, {"symbol": "META", "barTime": "2023-04-27 21:30", "content": "BUY@236.26 Size:2", "strategy": "Revival (BUY:SMA30 SELL:BollTop TF:60)", "upTime": "2023-05-07 03:49", "key": 205}, {"symbol": "GOOGL", "barTime": "2023-04-27 21:30", "content": "BUY@105.23 Size:4", "strategy": "Revival (BUY:SMA30 SELL:BollTop TF:60)", "upTime": "2023-05-07 03:13", "key": 206}, {"symbol": "TQQQ", "barTime": "2023-04-27 21:30", "content": "BUY@26.53 Size:18", "strategy": "Revival (BUY:SMA30 SELL:BollTop TF:60)", "upTime": "2023-05-07 03:49", "key": 207}, {"symbol": "LRCX", "barTime": "2023-04-27 03:30", "content": "BUY@492.43 Size:1", "strategy": "Vivid (BollBot x BollTop TF:60)", "upTime": "2023-05-07 03:49", "key": 208}, {"symbol": "GOOGL", "barTime": "2023-04-27 02:30", "content": "BUY@102.52 Size:4", "strategy": "Vivid (BollBot x BollTop TF:60)", "upTime": "2023-05-07 03:13", "key": 209}, {"symbol": "EDU", "barTime": "2023-04-27 02:30", "content": "SELL@45.32 Size:0 Gain:0.00%", "strategy": "Vivid (BollBot x BollTop TF:60)", "upTime": "2023-05-07 03:49", "key": 210}, {"symbol": "EDU", "barTime": "2023-04-27 01:30", "content": "SELL@45.76 Size:9 Gain:14.27%", "strategy": "Revival (BUY:SMA30 SELL:BollTop TF:60)", "upTime": "2023-05-07 03:49", "key": 211}, {"symbol": "MSFT", "barTime": "2023-04-27 01:30", "content": "SELL@295.98 Size:1 Gain:6.01%", "strategy": "Vivid (BollBot x BollTop TF:60)", "upTime": "2023-05-07 03:13", "key": 212}, {"symbol": "TSLA", "barTime": "2023-04-27 00:30", "content": "BUY@155.27 Size:3", "strategy": "Vivid (BollBot x BollTop TF:60)", "upTime": "2023-05-07 03:49", "key": 213}, {"symbol": "MSFT", "barTime": "2023-04-27 00:30", "content": "SELL@297.22 Size:1 Gain:4.43%", "strategy": "Revival (BUY:SMA30 SELL:BollTop TF:60)", "upTime": "2023-05-07 03:13", "key": 214}, {"symbol": "MNST", "barTime": "2023-04-26 23:30", "content": "SELL@54.52 Size:0 Gain:0.00%", "strategy": "Vivid (BollBot x BollTop TF:60)", "upTime": "2023-05-07 03:30", "key": 215}, {"symbol": "NVDA", "barTime": "2023-04-26 22:30", "content": "BUY@269.26 Size:1", "strategy": "Revival (BUY:SMA30 SELL:BollTop TF:60)", "upTime": "2023-05-07 03:30", "key": 216}, {"symbol": "AAPL", "barTime": "2023-04-26 22:30", "content": "BUY@162.97 Size:3", "strategy": "Vivid (BollBot x BollTop TF:60)", "upTime": "2023-05-07 03:49", "key": 217}, {"symbol": "META", "barTime": "2023-04-26 22:30", "content": "BUY@210.66 Size:2", "strategy": "Revival (BUY:SMA30 SELL:BollTop TF:60)", "upTime": "2023-05-07 03:49", "key": 218}, {"symbol": "UPRO", "barTime": "2023-04-26 22:30", "content": "BUY@37.19 Size:13", "strategy": "Vivid (BollBot x BollTop TF:60)", "upTime": "2023-05-07 03:49", "key": 219}, {"symbol": "LABU", "barTime": "2023-04-26 22:30", "content": "BUY@5.36 Size:93", "strategy": "Vivid (BollBot x BollTop TF:60)", "upTime": "2023-05-07 03:30", "key": 220}, {"symbol": "SSO", "barTime": "2023-04-26 22:30", "content": "BUY@48.92 Size:10", "strategy": "Vivid (BollBot x BollTop TF:60)", "upTime": "2023-05-07 03:13", "key": 221}, {"symbol": "KO", "barTime": "2023-04-26 22:30", "content": "BUY@62.93 Size:7", "strategy": "Vivid (BollBot x BollTop TF:60)", "upTime": "2023-05-07 03:30", "key": 222}, {"symbol": "AMZN", "barTime": "2023-04-26 21:30", "content": "BUY@104.62 Size:4", "strategy": "Revival (BUY:SMA30 SELL:BollTop TF:60)", "upTime": "2023-05-07 03:49", "key": 223}, {"symbol": "QQQ", "barTime": "2023-04-26 21:30", "content": "BUY@309.54 Size:1", "strategy": "Vivid (BollBot x BollTop TF:60)", "upTime": "2023-05-07 03:13", "key": 224}, {"symbol": "NVDA", "barTime": "2023-04-26 21:30", "content": "BUY@267.42 Size:1", "strategy": "Vivid (BollBot x BollTop TF:60)", "upTime": "2023-05-07 03:49", "key": 225}, {"symbol": "AMZN", "barTime": "2023-04-26 21:30", "content": "BUY@104.62 Size:4", "strategy": "Vivid (BollBot x BollTop TF:60)", "upTime": "2023-05-07 03:49", "key": 226}, {"symbol": "MSFT", "barTime": "2023-04-26 21:30", "content": "BUY@292.37 Size:1", "strategy": "Revival (BUY:SMA30 SELL:BollTop TF:60)", "upTime": "2023-05-07 03:13", "key": 227}, {"symbol": "GOOGL", "barTime": "2023-04-26 21:30", "content": "BUY@104.28 Size:4", "strategy": "Revival (BUY:SMA30 SELL:BollTop TF:60)", "upTime": "2023-05-07 03:13", "key": 228}, {"symbol": "TCEHY", "barTime": "2023-04-26 21:30", "content": "BUY@43.52 Size:11", "strategy": "Revival (BUY:SMA30 SELL:BollTop TF:60)", "upTime": "2023-05-07 03:13", "key": 229}, {"symbol": "EDU", "barTime": "2023-04-26 21:30", "content": "BUY@45.18 Size:11", "strategy": "Revival (BUY:SMA30 SELL:BollTop TF:60)", "upTime": "2023-05-07 03:49", "key": 230}, {"symbol": "META", "barTime": "2023-04-26 21:30", "content": "BUY@209.21 Size:2", "strategy": "Vivid (BollBot x BollTop TF:60)", "upTime": "2023-05-07 03:49", "key": 231}, {"symbol": "MSFT", "barTime": "2023-04-26 21:30", "content": "BUY@292.37 Size:1", "strategy": "Vivid (BollBot x BollTop TF:60)", "upTime": "2023-05-07 03:13", "key": 232}, {"symbol": "GOOGL", "barTime": "2023-04-26 21:30", "content": "BUY@104.28 Size:4", "strategy": "Vivid (BollBot x BollTop TF:60)", "upTime": "2023-05-07 03:13", "key": 233}, {"symbol": "SOXL", "barTime": "2023-04-26 21:30", "content": "BUY@13.32 Size:37", "strategy": "Vivid (BollBot x BollTop TF:60)", "upTime": "2023-05-07 03:49", "key": 234}, {"symbol": "TQQQ", "barTime": "2023-04-26 21:30", "content": "BUY@25.58 Size:19", "strategy": "Vivid (BollBot x BollTop TF:60)", "upTime": "2023-05-07 03:49", "key": 235}, {"symbol": "LRCX", "barTime": "2023-04-26 21:30", "content": "BUY@498.66 Size:1", "strategy": "Vivid (BollBot x BollTop TF:60)", "upTime": "2023-05-07 03:49", "key": 236}, {"symbol": "ASML", "barTime": "2023-04-26 03:30", "content": "BUY@599.70 Size:0", "strategy": "Vivid (BollBot x BollTop TF:60)", "upTime": "2023-05-07 03:13", "key": 237}, {"symbol": "AMZN", "barTime": "2023-04-26 02:30", "content": "BUY@102.00 Size:4", "strategy": "Vivid (BollBot x BollTop TF:60)", "upTime": "2023-05-07 03:49", "key": 238}, {"symbol": "NUGT", "barTime": "2023-04-26 02:30", "content": "BUY@44.87 Size:11", "strategy": "Revival (BUY:SMA30 SELL:BollTop TF:60)", "upTime": "2023-05-07 03:49", "key": 239}, {"symbol": "MSFT", "barTime": "2023-04-26 02:30", "content": "BUY@273.51 Size:1", "strategy": "Vivid (BollBot x BollTop TF:60)", "upTime": "2023-05-07 03:13", "key": 240}, {"symbol": "SMH", "barTime": "2023-04-26 02:30", "content": "BUY@118.82 Size:4", "strategy": "Vivid (BollBot x BollTop TF:60)", "upTime": "2023-05-07 03:30", "key": 241}, {"symbol": "LABU", "barTime": "2023-04-26 02:30", "content": "BUY@5.47 Size:91", "strategy": "Vivid (BollBot x BollTop TF:60)", "upTime": "2023-05-07 03:30", "key": 242}, {"symbol": "NVDA", "barTime": "2023-04-26 01:30", "content": "BUY@262.01 Size:1", "strategy": "Vivid (BollBot x BollTop TF:60)", "upTime": "2023-05-07 03:49", "key": 243}, {"symbol": "LRCX", "barTime": "2023-04-26 01:30", "content": "BUY@499.33 Size:1", "strategy": "Vivid (BollBot x BollTop TF:60)", "upTime": "2023-05-07 03:49", "key": 244}, {"symbol": "NKE", "barTime": "2023-04-26 01:30", "content": "BUY@123.18 Size:4", "strategy": "Vivid (BollBot x BollTop TF:60)", "upTime": "2023-05-07 03:13", "key": 245}, {"symbol": "MSFT", "barTime": "2023-04-26 00:30", "content": "BUY@275.56 Size:1", "strategy": "Vivid (BollBot x BollTop TF:60)", "upTime": "2023-05-07 03:13", "key": 246}, {"symbol": "MNST", "barTime": "2023-04-26 00:30", "content": "SELL@54.09 Size:0 Gain:0.00%", "strategy": "Vivid (BollBot x BollTop TF:60)", "upTime": "2023-05-07 03:30", "key": 247}, {"symbol": "MNST", "barTime": "2023-04-25 23:30", "content": "SELL@54.22 Size:8 Gain:6.43%", "strategy": "Revival (BUY:SMA30 SELL:BollTop TF:60)", "upTime": "2023-05-07 03:49", "key": 248}, {"symbol": "KO", "barTime": "2023-04-25 22:30", "content": "BUY@63.36 Size:7", "strategy": "Revival (BUY:SMA30 SELL:BollTop TF:60)", "upTime": "2023-05-07 03:49", "key": 249}, {"symbol": "MSFT", "barTime": "2023-04-25 22:30", "content": "BUY@276.58 Size:1", "strategy": "Vivid (BollBot x BollTop TF:60)", "upTime": "2023-05-07 03:13", "key": 250}, {"symbol": "NUGT", "barTime": "2023-04-25 22:30", "content": "BUY@44.07 Size:11", "strategy": "Vivid (BollBot x BollTop TF:60)", "upTime": "2023-05-07 03:49", "key": 251}, {"symbol": "TCEHY", "barTime": "2023-04-25 22:30", "content": "BUY@42.20 Size:11", "strategy": "Vivid (BollBot x BollTop TF:60)", "upTime": "2023-05-07 03:13", "key": 252}, {"symbol": "EDU", "barTime": "2023-04-25 22:30", "content": "BUY@42.56 Size:11", "strategy": "Vivid (BollBot x BollTop TF:60)", "upTime": "2023-05-07 03:49", "key": 253}, {"symbol": "NKE", "barTime": "2023-04-25 21:30", "content": "SELL@126.25 Size:3 Gain:4.41%", "strategy": "Revival (BUY:SMA30 SELL:BollTop TF:60)", "upTime": "2023-05-07 03:13", "key": 254}, {"symbol": "NKE", "barTime": "2023-04-25 21:30", "content": "SELL@126.25 Size:3 Gain:1.65%", "strategy": "Vivid (BollBot x BollTop TF:60)", "upTime": "2023-05-07 03:13", "key": 255}, {"symbol": "LABU", "barTime": "2023-04-25 03:30", "content": "BUY@5.77 Size:86", "strategy": "Revival (BUY:SMA30 SELL:BollTop TF:60)", "upTime": "2023-05-07 03:49", "key": 256}, {"symbol": "KO", "barTime": "2023-04-25 03:30", "content": "BUY@63.31 Size:7", "strategy": "Revival (BUY:SMA30 SELL:BollTop TF:60)", "upTime": "2023-05-07 03:49", "key": 257}, {"symbol": "KO", "barTime": "2023-04-25 03:30", "content": "BUY@63.31 Size:7", "strategy": "Vivid (BollBot x BollTop TF:60)", "upTime": "2023-05-07 03:30", "key": 258}, {"symbol": "GOOGL", "barTime": "2023-04-25 02:30", "content": "SELL@106.16 Size:0 Gain:0.00%", "strategy": "Vivid (BollBot x BollTop TF:60)", "upTime": "2023-05-07 03:13", "key": 259}, {"symbol": "LABU", "barTime": "2023-04-25 01:30", "content": "BUY@5.77 Size:86", "strategy": "Revival (BUY:SMA30 SELL:BollTop TF:60)", "upTime": "2023-05-07 03:49", "key": 260}, {"symbol": "MSFT", "barTime": "2023-04-25 01:30", "content": "BUY@278.55 Size:1", "strategy": "Vivid (BollBot x BollTop TF:60)", "upTime": "2023-05-07 03:13", "key": 261}, {"symbol": "TQQQ", "barTime": "2023-04-25 00:30", "content": "BUY@26.20 Size:19", "strategy": "Vivid (BollBot x BollTop TF:60)", "upTime": "2023-05-07 03:49", "key": 262}, {"symbol": "MNST", "barTime": "2023-04-25 00:30", "content": "SELL@53.58 Size:0 Gain:0.00%", "strategy": "Vivid (BollBot x BollTop TF:60)", "upTime": "2023-05-07 03:30", "key": 263}, {"symbol": "TCEHY", "barTime": "2023-04-25 00:30", "content": "BUY@42.71 Size:11", "strategy": "Vivid (BollBot x BollTop TF:60)", "upTime": "2023-05-07 03:13", "key": 264}, {"symbol": "QQQ", "barTime": "2023-04-24 23:30", "content": "BUY@311.41 Size:1", "strategy": "Vivid (BollBot x BollTop TF:60)", "upTime": "2023-05-07 03:13", "key": 265}, {"symbol": "MNST", "barTime": "2023-04-24 23:30", "content": "SELL@53.65 Size:8 Gain:5.32%", "strategy": "Revival (BUY:SMA30 SELL:BollTop TF:60)", "upTime": "2023-05-07 03:49", "key": 266}, {"symbol": "NKE", "barTime": "2023-04-24 23:30", "content": "BUY@124.51 Size:4", "strategy": "Revival (BUY:SMA30 SELL:BollTop TF:60)", "upTime": "2023-05-07 03:13", "key": 267}, {"symbol": "SMH", "barTime": "2023-04-24 23:30", "content": "BUY@121.80 Size:4", "strategy": "Vivid (BollBot x BollTop TF:60)", "upTime": "2023-05-07 03:30", "key": 268}, {"symbol": "SOXL", "barTime": "2023-04-24 23:30", "content": "BUY@14.34 Size:34", "strategy": "Vivid (BollBot x BollTop TF:60)", "upTime": "2023-05-07 03:49", "key": 269}, {"symbol": "KO", "barTime": "2023-04-24 23:30", "content": "SELL@64.09 Size:0 Gain:0.00%", "strategy": "Vivid (BollBot x BollTop TF:60)", "upTime": "2023-05-07 03:30", "key": 270}, {"symbol": "GOOGL", "barTime": "2023-04-24 22:30", "content": "SELL@105.59 Size:4 Gain:0.76%", "strategy": "Revival (BUY:SMA30 SELL:BollTop TF:60)", "upTime": "2023-05-07 03:13", "key": 271}, {"symbol": "NFLX", "barTime": "2023-04-24 22:30", "content": "SELL@328.71 Size:1 Gain:0.46%", "strategy": "Revival (BUY:SMA30 SELL:BollTop TF:60)", "upTime": "2023-05-07 03:13", "key": 272}, {"symbol": "GOOGL", "barTime": "2023-04-24 22:30", "content": "SELL@105.59 Size:0 Gain:0.00%", "strategy": "Vivid (BollBot x BollTop TF:60)", "upTime": "2023-05-07 03:13", "key": 273}, {"symbol": "NFLX", "barTime": "2023-04-24 22:30", "content": "SELL@328.71 Size:1 Gain:1.64%", "strategy": "Vivid (BollBot x BollTop TF:60)", "upTime": "2023-05-07 03:13", "key": 274}, {"symbol": "ASML", "barTime": "2023-04-22 03:30", "content": "BUY@628.13 Size:0", "strategy": "Revival (BUY:SMA30 SELL:BollTop TF:60)", "upTime": "2023-05-07 03:13", "key": 275}, {"symbol": "NKE", "barTime": "2023-04-22 03:30", "content": "BUY@124.27 Size:4", "strategy": "Revival (BUY:SMA30 SELL:BollTop TF:60)", "upTime": "2023-05-07 03:13", "key": 276}, {"symbol": "AMZN", "barTime": "2023-04-22 02:30", "content": "SELL@106.92 Size:2 Gain:8.52%", "strategy": "Vivid (BollBot x BollTop TF:60)", "upTime": "2023-05-07 03:49", "key": 277}, {"symbol": "MNST", "barTime": "2023-04-22 02:30", "content": "SELL@53.17 Size:0 Gain:0.00%", "strategy": "Vivid (BollBot x BollTop TF:60)", "upTime": "2023-05-07 03:30", "key": 278}, {"symbol": "AMZN", "barTime": "2023-04-22 01:30", "content": "SELL@107.81 Size:4 Gain:12.16%", "strategy": "Revival (BUY:SMA30 SELL:BollTop TF:60)", "upTime": "2023-05-07 03:49", "key": 279}, {"symbol": "AAPL", "barTime": "2023-04-22 01:30", "content": "BUY@163.62 Size:3", "strategy": "Vivid (BollBot x BollTop TF:60)", "upTime": "2023-05-07 03:49", "key": 280}, {"symbol": "NFLX", "barTime": "2023-04-22 01:30", "content": "BUY@324.11 Size:1", "strategy": "Revival (BUY:SMA30 SELL:BollTop TF:60)", "upTime": "2023-05-07 03:13", "key": 281}, {"symbol": "ASML", "barTime": "2023-04-22 01:30", "content": "BUY@629.52 Size:0", "strategy": "Revival (BUY:SMA30 SELL:BollTop TF:60)", "upTime": "2023-05-07 03:13", "key": 282}, {"symbol": "TCEHY", "barTime": "2023-04-22 01:30", "content": "BUY@43.73 Size:11", "strategy": "Vivid (BollBot x BollTop TF:60)", "upTime": "2023-05-07 03:13", "key": 283}, {"symbol": "KO", "barTime": "2023-04-22 01:30", "content": "SELL@64.10 Size:0 Gain:0.00%", "strategy": "Vivid (BollBot x BollTop TF:60)", "upTime": "2023-05-07 03:30", "key": 284}, {"symbol": "NUGT", "barTime": "2023-04-22 00:30", "content": "BUY@44.27 Size:11", "strategy": "Vivid (BollBot x BollTop TF:60)", "upTime": "2023-05-07 03:49", "key": 285}, {"symbol": "NVDA", "barTime": "2023-04-21 23:30", "content": "BUY@267.68 Size:1", "strategy": "Vivid (BollBot x BollTop TF:60)", "upTime": "2023-05-07 03:49", "key": 286}, {"symbol": "MSFT", "barTime": "2023-04-21 23:30", "content": "BUY@282.37 Size:1", "strategy": "Vivid (BollBot x BollTop TF:60)", "upTime": "2023-05-07 03:13", "key": 287}, {"symbol": "SMH", "barTime": "2023-04-21 23:30", "content": "BUY@122.88 Size:4", "strategy": "Vivid (BollBot x BollTop TF:60)", "upTime": "2023-05-07 03:30", "key": 288}, {"symbol": "SOXL", "barTime": "2023-04-21 23:30", "content": "BUY@14.63 Size:34", "strategy": "Vivid (BollBot x BollTop TF:60)", "upTime": "2023-05-07 03:49", "key": 289}, {"symbol": "LABU", "barTime": "2023-04-21 22:30", "content": "BUY@5.78 Size:86", "strategy": "Revival (BUY:SMA30 SELL:BollTop TF:60)", "upTime": "2023-05-07 03:49", "key": 290}, {"symbol": "ASML", "barTime": "2023-04-21 22:30", "content": "BUY@628.80 Size:0", "strategy": "Revival (BUY:SMA30 SELL:BollTop TF:60)", "upTime": "2023-05-07 03:13", "key": 291}, {"symbol": "META", "barTime": "2023-04-21 22:30", "content": "BUY@210.26 Size:2", "strategy": "Vivid (BollBot x BollTop TF:60)", "upTime": "2023-05-07 03:49", "key": 292}, {"symbol": "KO", "barTime": "2023-04-21 22:30", "content": "SELL@63.86 Size:0 Gain:0.00%", "strategy": "Vivid (BollBot x BollTop TF:60)", "upTime": "2023-05-07 03:30", "key": 293}, {"symbol": "AAPL", "barTime": "2023-04-21 03:30", "content": "BUY@164.98 Size:3", "strategy": "Revival (BUY:SMA30 SELL:BollTop TF:60)", "upTime": "2023-05-07 03:49", "key": 294}, {"symbol": "QQQ", "barTime": "2023-04-21 03:30", "content": "BUY@313.12 Size:1", "strategy": "Vivid (BollBot x BollTop TF:60)", "upTime": "2023-05-07 03:13", "key": 295}, {"symbol": "AAPL", "barTime": "2023-04-21 03:30", "content": "BUY@164.98 Size:3", "strategy": "Vivid (BollBot x BollTop TF:60)", "upTime": "2023-05-07 03:49", "key": 296}, {"symbol": "GOOGL", "barTime": "2023-04-21 03:30", "content": "BUY@104.24 Size:4", "strategy": "Revival (BUY:SMA30 SELL:BollTop TF:60)", "upTime": "2023-05-07 03:13", "key": 297}, {"symbol": "MSFT", "barTime": "2023-04-21 03:30", "content": "BUY@283.25 Size:1", "strategy": "Vivid (BollBot x BollTop TF:60)", "upTime": "2023-05-07 03:13", "key": 298}, {"symbol": "SOXL", "barTime": "2023-04-21 03:30", "content": "BUY@15.05 Size:33", "strategy": "Vivid (BollBot x BollTop TF:60)", "upTime": "2023-05-07 03:49", "key": 299}, {"symbol": "TQQQ", "barTime": "2023-04-21 03:30", "content": "BUY@26.55 Size:18", "strategy": "Vivid (BollBot x BollTop TF:60)", "upTime": "2023-05-07 03:49", "key": 300}, {"symbol": "UPRO", "barTime": "2023-04-21 03:30", "content": "BUY@38.58 Size:12", "strategy": "Vivid (BollBot x BollTop TF:60)", "upTime": "2023-05-07 03:49", "key": 301}, {"symbol": "SSO", "barTime": "2023-04-21 03:30", "content": "BUY@50.13 Size:9", "strategy": "Vivid (BollBot x BollTop TF:60)", "upTime": "2023-05-07 03:13", "key": 302}, {"symbol": "NKE", "barTime": "2023-04-21 03:30", "content": "BUY@123.21 Size:4", "strategy": "Vivid (BollBot x BollTop TF:60)", "upTime": "2023-05-07 03:13", "key": 303}, {"symbol": "TSLA", "barTime": "2023-04-21 02:30", "content": "BUY@159.47 Size:3", "strategy": "Vivid (BollBot x BollTop TF:60)", "upTime": "2023-05-07 03:49", "key": 304}, {"symbol": "GOOGL", "barTime": "2023-04-21 01:30", "content": "SELL@105.14 Size:4 Gain:0.34%", "strategy": "Revival (BUY:SMA30 SELL:BollTop TF:60)", "upTime": "2023-05-07 03:13", "key": 305}, {"symbol": "MNST", "barTime": "2023-04-21 01:30", "content": "SELL@52.88 Size:8 Gain:3.81%", "strategy": "Revival (BUY:SMA30 SELL:BollTop TF:60)", "upTime": "2023-05-07 03:49", "key": 306}, {"symbol": "LRCX", "barTime": "2023-04-21 01:30", "content": "SELL@529.00 Size:1 Gain:8.03%", "strategy": "Revival (BUY:SMA30 SELL:BollTop TF:60)", "upTime": "2023-05-07 03:49", "key": 307}, {"symbol": "KO", "barTime": "2023-04-21 01:30", "content": "SELL@63.96 Size:6 Gain:7.32%", "strategy": "Revival (BUY:SMA30 SELL:BollTop TF:60)", "upTime": "2023-05-07 03:49", "key": 308}, {"symbol": "GOOGL", "barTime": "2023-04-21 01:30", "content": "SELL@105.14 Size:0 Gain:0.00%", "strategy": "Vivid (BollBot x BollTop TF:60)", "upTime": "2023-05-07 03:13", "key": 309}, {"symbol": "SMH", "barTime": "2023-04-21 01:30", "content": "SELL@126.17 Size:3 Gain:0.49%", "strategy": "Vivid (BollBot x BollTop TF:60)", "upTime": "2023-05-07 03:30", "key": 310}, {"symbol": "MNST", "barTime": "2023-04-21 01:30", "content": "SELL@52.88 Size:0 Gain:0.00%", "strategy": "Vivid (BollBot x BollTop TF:60)", "upTime": "2023-05-07 03:30", "key": 311}, {"symbol": "LRCX", "barTime": "2023-04-21 01:30", "content": "SELL@529.00 Size:1 Gain:7.32%", "strategy": "Vivid (BollBot x BollTop TF:60)", "upTime": "2023-05-07 03:49", "key": 312}, {"symbol": "KO", "barTime": "2023-04-21 01:30", "content": "SELL@63.96 Size:0 Gain:0.00%", "strategy": "Vivid (BollBot x BollTop TF:60)", "upTime": "2023-05-07 03:30", "key": 313}, {"symbol": "QQQ", "barTime": "2023-04-21 00:30", "content": "BUY@315.87 Size:1", "strategy": "Revival (BUY:SMA30 SELL:BollTop TF:60)", "upTime": "2023-05-07 03:13", "key": 314}, {"symbol": "GOOGL", "barTime": "2023-04-21 00:30", "content": "BUY@105.16 Size:4", "strategy": "Revival (BUY:SMA30 SELL:BollTop TF:60)", "upTime": "2023-05-07 03:13", "key": 315}, {"symbol": "TQQQ", "barTime": "2023-04-21 00:30", "content": "BUY@27.25 Size:18", "strategy": "Revival (BUY:SMA30 SELL:BollTop TF:60)", "upTime": "2023-05-07 03:49", "key": 316}, {"symbol": "UPRO", "barTime": "2023-04-21 00:30", "content": "BUY@39.07 Size:12", "strategy": "Revival (BUY:SMA30 SELL:BollTop TF:60)", "upTime": "2023-05-07 03:49", "key": 317}, {"symbol": "LABU", "barTime": "2023-04-21 00:30", "content": "BUY@5.71 Size:87", "strategy": "Revival (BUY:SMA30 SELL:BollTop TF:60)", "upTime": "2023-05-07 03:49", "key": 318}, {"symbol": "SSO", "barTime": "2023-04-21 00:30", "content": "BUY@50.52 Size:9", "strategy": "Revival (BUY:SMA30 SELL:BollTop TF:60)", "upTime": "2023-05-07 03:13", "key": 319}, {"symbol": "NFLX", "barTime": "2023-04-21 00:30", "content": "BUY@327.69 Size:1", "strategy": "Revival (BUY:SMA30 SELL:BollTop TF:60)", "upTime": "2023-05-07 03:13", "key": 320}, {"symbol": "QQQ", "barTime": "2023-04-20 23:30", "content": "BUY@314.79 Size:1", "strategy": "Vivid (BollBot x BollTop TF:60)", "upTime": "2023-05-07 03:13", "key": 321}, {"symbol": "MSFT", "barTime": "2023-04-20 23:30", "content": "BUY@284.87 Size:1", "strategy": "Revival (BUY:SMA30 SELL:BollTop TF:60)", "upTime": "2023-05-07 03:13", "key": 322}, {"symbol": "SOXL", "barTime": "2023-04-20 23:30", "content": "BUY@15.42 Size:32", "strategy": "Revival (BUY:SMA30 SELL:BollTop TF:60)", "upTime": "2023-05-07 03:30", "key": 323}, {"symbol": "MNST", "barTime": "2023-04-20 23:30", "content": "SELL@52.99 Size:8 Gain:4.02%", "strategy": "Revival (BUY:SMA30 SELL:BollTop TF:60)", "upTime": "2023-05-07 03:49", "key": 324}, {"symbol": "EDU", "barTime": "2023-04-20 23:30", "content": "SELL@44.16 Size:9 Gain:12.89%", "strategy": "Revival (BUY:SMA30 SELL:BollTop TF:60)", "upTime": "2023-05-07 03:49", "key": 325}, {"symbol": "KO", "barTime": "2023-04-20 23:30", "content": "SELL@63.89 Size:6 Gain:7.21%", "strategy": "Revival (BUY:SMA30 SELL:BollTop TF:60)", "upTime": "2023-05-07 03:49", "key": 326}, {"symbol": "TQQQ", "barTime": "2023-04-20 23:30", "content": "BUY@26.97 Size:18", "strategy": "Vivid (BollBot x BollTop TF:60)", "upTime": "2023-05-07 03:49", "key": 327}, {"symbol": "UPRO", "barTime": "2023-04-20 23:30", "content": "BUY@38.80 Size:12", "strategy": "Vivid (BollBot x BollTop TF:60)", "upTime": "2023-05-07 03:49", "key": 328}, {"symbol": "SSO", "barTime": "2023-04-20 23:30", "content": "BUY@50.30 Size:9", "strategy": "Vivid (BollBot x BollTop TF:60)", "upTime": "2023-05-07 03:13", "key": 329}, {"symbol": "NKE", "barTime": "2023-04-20 23:30", "content": "BUY@123.78 Size:4", "strategy": "Vivid (BollBot x BollTop TF:60)", "upTime": "2023-05-07 03:13", "key": 330}, {"symbol": "EDU", "barTime": "2023-04-20 23:30", "content": "SELL@44.16 Size:8 Gain:18.22%", "strategy": "Vivid (BollBot x BollTop TF:60)", "upTime": "2023-05-07 03:49", "key": 331}, {"symbol": "SMH", "barTime": "2023-04-20 21:30", "content": "BUY@124.82 Size:4", "strategy": "Revival (BUY:SMA30 SELL:BollTop TF:60)", "upTime": "2023-05-07 03:30", "key": 332}, {"symbol": "MNST", "barTime": "2023-04-20 21:30", "content": "BUY@52.23 Size:9", "strategy": "Revival (BUY:SMA30 SELL:BollTop TF:60)", "upTime": "2023-05-07 03:49", "key": 333}, {"symbol": "LRCX", "barTime": "2023-04-20 21:30", "content": "BUY@516.51 Size:0", "strategy": "Revival (BUY:SMA30 SELL:BollTop TF:60)", "upTime": "2023-05-07 03:49", "key": 334}, {"symbol": "AMZN", "barTime": "2023-04-20 03:30", "content": "SELL@104.30 Size:4 Gain:5.86%", "strategy": "Vivid (BollBot x BollTop TF:60)", "upTime": "2023-05-07 03:49", "key": 335}, {"symbol": "LABU", "barTime": "2023-04-20 03:30", "content": "SELL@5.97 Size:70 Gain:2.31%", "strategy": "Revival (BUY:SMA30 SELL:BollTop TF:60)", "upTime": "2023-05-07 03:49", "key": 336}, {"symbol": "EDU", "barTime": "2023-04-20 03:30", "content": "SELL@42.71 Size:10 Gain:9.18%", "strategy": "Revival (BUY:SMA30 SELL:BollTop TF:60)", "upTime": "2023-05-07 03:49", "key": 337}, {"symbol": "LABU", "barTime": "2023-04-20 03:30", "content": "SELL@5.97 Size:70 Gain:-9.90%", "strategy": "Vivid (BollBot x BollTop TF:60)", "upTime": "2023-05-07 03:30", "key": 338}, {"symbol": "EDU", "barTime": "2023-04-20 03:30", "content": "SELL@42.71 Size:10 Gain:14.34%", "strategy": "Vivid (BollBot x BollTop TF:60)", "upTime": "2023-05-07 03:49", "key": 339}, {"symbol": "AMZN", "barTime": "2023-04-20 02:30", "content": "SELL@104.98 Size:4 Gain:9.23%", "strategy": "Revival (BUY:SMA30 SELL:BollTop TF:60)", "upTime": "2023-05-07 03:49", "key": 340}, {"symbol": "NFLX", "barTime": "2023-04-20 02:30", "content": "BUY@318.23 Size:1", "strategy": "Vivid (BollBot x BollTop TF:60)", "upTime": "2023-05-07 03:13", "key": 341}, {"symbol": "NUGT", "barTime": "2023-04-20 02:30", "content": "BUY@45.48 Size:10", "strategy": "Vivid (BollBot x BollTop TF:60)", "upTime": "2023-05-07 03:49", "key": 342}, {"symbol": "AAPL", "barTime": "2023-04-20 01:30", "content": "SELL@167.90 Size:0 Gain:0.00%", "strategy": "Vivid (BollBot x BollTop TF:60)", "upTime": "2023-05-07 03:49", "key": 343}, {"symbol": "AAPL", "barTime": "2023-04-20 00:30", "content": "SELL@167.92 Size:2 Gain:8.91%", "strategy": "Revival (BUY:SMA30 SELL:BollTop TF:60)", "upTime": "2023-05-07 03:49", "key": 344}, {"symbol": "TCEHY", "barTime": "2023-04-20 00:30", "content": "BUY@45.11 Size:11", "strategy": "Vivid (BollBot x BollTop TF:60)", "upTime": "2023-05-07 03:13", "key": 345}, {"symbol": "QQQ", "barTime": "2023-04-19 23:30", "content": "BUY@315.76 Size:1", "strategy": "Revival (BUY:SMA30 SELL:BollTop TF:60)", "upTime": "2023-05-07 03:13", "key": 346}, {"symbol": "TSLA", "barTime": "2023-04-19 23:30", "content": "BUY@180.15 Size:2", "strategy": "Vivid (BollBot x BollTop TF:60)", "upTime": "2023-05-07 03:49", "key": 347}, {"symbol": "TQQQ", "barTime": "2023-04-19 23:30", "content": "BUY@27.25 Size:18", "strategy": "Revival (BUY:SMA30 SELL:BollTop TF:60)", "upTime": "2023-05-07 03:49", "key": 348}, {"symbol": "MNST", "barTime": "2023-04-19 23:30", "content": "BUY@52.07 Size:9", "strategy": "Revival (BUY:SMA30 SELL:BollTop TF:60)", "upTime": "2023-05-07 03:49", "key": 349}, {"symbol": "META", "barTime": "2023-04-19 23:30", "content": "BUY@213.57 Size:2", "strategy": "Vivid (BollBot x BollTop TF:60)", "upTime": "2023-05-07 03:49", "key": 350}, {"symbol": "ASML", "barTime": "2023-04-19 23:30", "content": "BUY@618.28 Size:0", "strategy": "Vivid (BollBot x BollTop TF:60)", "upTime": "2023-05-07 03:13", "key": 351}, {"symbol": "MSFT", "barTime": "2023-04-19 22:30", "content": "BUY@284.61 Size:1", "strategy": "Revival (BUY:SMA30 SELL:BollTop TF:60)", "upTime": "2023-05-07 03:13", "key": 352}, {"symbol": "EDU", "barTime": "2023-04-19 22:30", "content": "SELL@39.91 Size:10 Gain:2.03%", "strategy": "Revival (BUY:SMA30 SELL:BollTop TF:60)", "upTime": "2023-05-07 03:49", "key": 353}, {"symbol": "EDU", "barTime": "2023-04-19 22:30", "content": "SELL@39.91 Size:10 Gain:6.85%", "strategy": "Vivid (BollBot x BollTop TF:60)", "upTime": "2023-05-07 03:49", "key": 354}, {"symbol": "KO", "barTime": "2023-04-19 22:30", "content": "SELL@63.58 Size:0 Gain:0.00%", "strategy": "Vivid (BollBot x BollTop TF:60)", "upTime": "2023-05-07 03:30", "key": 355}, {"symbol": "LRCX", "barTime": "2023-04-19 03:30", "content": "BUY@490.42 Size:1", "strategy": "Revival (BUY:SMA30 SELL:BollTop TF:60)", "upTime": "2023-05-07 03:49", "key": 356}, {"symbol": "AAPL", "barTime": "2023-04-19 02:30", "content": "SELL@166.38 Size:2 Gain:7.91%", "strategy": "Revival (BUY:SMA30 SELL:BollTop TF:60)", "upTime": "2023-05-07 03:49", "key": 357}, {"symbol": "AAPL", "barTime": "2023-04-19 02:30", "content": "SELL@166.38 Size:2 Gain:3.66%", "strategy": "Vivid (BollBot x BollTop TF:60)", "upTime": "2023-05-07 03:49", "key": 358}, {"symbol": "MNST", "barTime": "2023-04-19 02:30", "content": "BUY@52.09 Size:9", "strategy": "Revival (BUY:SMA30 SELL:BollTop TF:60)", "upTime": "2023-05-07 03:49", "key": 359}, {"symbol": "NKE", "barTime": "2023-04-19 02:30", "content": "SELL@126.47 Size:0 Gain:0.00%", "strategy": "Vivid (BollBot x BollTop TF:60)", "upTime": "2023-05-07 03:13", "key": 360}, {"symbol": "NVDA", "barTime": "2023-04-19 00:30", "content": "SELL@277.90 Size:1 Gain:2.67%", "strategy": "Revival (BUY:SMA30 SELL:BollTop TF:60)", "upTime": "2023-05-07 03:30", "key": 361}, {"symbol": "AAPL", "barTime": "2023-04-19 00:30", "content": "SELL@165.93 Size:2 Gain:3.37%", "strategy": "Vivid (BollBot x BollTop TF:60)", "upTime": "2023-05-07 03:49", "key": 362}, {"symbol": "NVDA", "barTime": "2023-04-19 00:30", "content": "SELL@277.90 Size:1 Gain:4.53%", "strategy": "Vivid (BollBot x BollTop TF:60)", "upTime": "2023-05-07 03:49", "key": 363}, {"symbol": "UPRO", "barTime": "2023-04-19 00:30", "content": "SELL@39.55 Size:6 Gain:13.64%", "strategy": "Vivid (BollBot x BollTop TF:60)", "upTime": "2023-05-07 03:49", "key": 364}, {"symbol": "NKE", "barTime": "2023-04-19 00:30", "content": "SELL@126.24 Size:0 Gain:0.00%", "strategy": "Vivid (BollBot x BollTop TF:60)", "upTime": "2023-05-07 03:13", "key": 365}, {"symbol": "TSLA", "barTime": "2023-04-18 22:30", "content": "BUY@183.36 Size:2", "strategy": "Revival (BUY:SMA30 SELL:BollTop TF:60)", "upTime": "2023-05-07 03:37", "key": 366}, {"symbol": "AAPL", "barTime": "2023-04-18 22:30", "content": "SELL@166.07 Size:2 Gain:7.71%", "strategy": "Revival (BUY:SMA30 SELL:BollTop TF:60)", "upTime": "2023-05-07 03:49", "key": 367}, {"symbol": "NKE", "barTime": "2023-04-18 22:30", "content": "BUY@124.62 Size:4", "strategy": "Revival (BUY:SMA30 SELL:BollTop TF:60)", "upTime": "2023-05-07 03:13", "key": 368}, {"symbol": "META", "barTime": "2023-04-18 22:30", "content": "BUY@215.42 Size:2", "strategy": "Vivid (BollBot x BollTop TF:60)", "upTime": "2023-05-07 03:49", "key": 369}, {"symbol": "NKE", "barTime": "2023-04-18 22:30", "content": "BUY@124.62 Size:4", "strategy": "Vivid (BollBot x BollTop TF:60)", "upTime": "2023-05-07 03:13", "key": 370}, {"symbol": "TSLA", "barTime": "2023-04-18 21:30", "content": "SELL@184.08 Size:2 Gain:0.59%", "strategy": "Vivid (BollBot x BollTop TF:60)", "upTime": "2023-05-07 03:49", "key": 371}, {"symbol": "SMH", "barTime": "2023-04-18 21:30", "content": "BUY@125.07 Size:3", "strategy": "Revival (BUY:SMA30 SELL:BollTop TF:60)", "upTime": "2023-05-07 03:30", "key": 372}, {"symbol": "SOXL", "barTime": "2023-04-18 21:30", "content": "BUY@15.55 Size:32", "strategy": "Revival (BUY:SMA30 SELL:BollTop TF:60)", "upTime": "2023-05-07 03:30", "key": 373}, {"symbol": "UPRO", "barTime": "2023-04-18 21:30", "content": "SELL@39.49 Size:10 Gain:13.46%", "strategy": "Vivid (BollBot x BollTop TF:60)", "upTime": "2023-05-07 03:49", "key": 374}, {"symbol": "SSO", "barTime": "2023-04-18 21:30", "content": "SELL@51.06 Size:0 Gain:0.00%", "strategy": "Vivid (BollBot x BollTop TF:60)", "upTime": "2023-05-07 03:13", "key": 375}, {"symbol": "TSLA", "barTime": "2023-04-18 02:30", "content": "BUY@184.69 Size:2", "strategy": "Revival (BUY:SMA30 SELL:BollTop TF:60)", "upTime": "2023-05-07 03:37", "key": 376}, {"symbol": "QQQ", "barTime": "2023-04-18 02:30", "content": "BUY@315.26 Size:1", "strategy": "Revival (BUY:SMA30 SELL:BollTop TF:60)", "upTime": "2023-05-07 03:13", "key": 377}, {"symbol": "NVDA", "barTime": "2023-04-18 02:30", "content": "BUY@266.32 Size:1", "strategy": "Revival (BUY:SMA30 SELL:BollTop TF:60)", "upTime": "2023-05-07 03:30", "key": 378}, {"symbol": "TQQQ", "barTime": "2023-04-18 02:30", "content": "BUY@27.14 Size:18", "strategy": "Revival (BUY:SMA30 SELL:BollTop TF:60)", "upTime": "2023-05-07 03:49", "key": 379}, {"symbol": "ASML", "barTime": "2023-04-18 02:30", "content": "BUY@632.97 Size:0", "strategy": "Vivid (BollBot x BollTop TF:60)", "upTime": "2023-05-07 03:13", "key": 380}, {"symbol": "EDU", "barTime": "2023-04-18 02:30", "content": "SELL@39.03 Size:11 Gain:4.49%", "strategy": "Vivid (BollBot x BollTop TF:60)", "upTime": "2023-05-07 03:49", "key": 381}, {"symbol": "EDU", "barTime": "2023-04-18 01:30", "content": "SELL@39.34 Size:11 Gain:0.56%", "strategy": "Revival (BUY:SMA30 SELL:BollTop TF:60)", "upTime": "2023-05-07 03:49", "key": 382}, {"symbol": "QQQ", "barTime": "2023-04-18 00:30", "content": "BUY@313.97 Size:1", "strategy": "Revival (BUY:SMA30 SELL:BollTop TF:60)", "upTime": "2023-05-07 03:13", "key": 383}, {"symbol": "TQQQ", "barTime": "2023-04-18 00:30", "content": "BUY@26.80 Size:18", "strategy": "Revival (BUY:SMA30 SELL:BollTop TF:60)", "upTime": "2023-05-07 03:49", "key": 384}, {"symbol": "SMH", "barTime": "2023-04-18 00:30", "content": "BUY@123.57 Size:4", "strategy": "Vivid (BollBot x BollTop TF:60)", "upTime": "2023-05-07 03:30", "key": 385}, {"symbol": "SOXL", "barTime": "2023-04-18 00:30", "content": "BUY@15.02 Size:33", "strategy": "Vivid (BollBot x BollTop TF:60)", "upTime": "2023-05-07 03:49", "key": 386}, {"symbol": "LRCX", "barTime": "2023-04-18 00:30", "content": "BUY@481.13 Size:1", "strategy": "Vivid (BollBot x BollTop TF:60)", "upTime": "2023-05-07 03:49", "key": 387}, {"symbol": "NFLX", "barTime": "2023-04-18 00:30", "content": "BUY@326.83 Size:1", "strategy": "Vivid (BollBot x BollTop TF:60)", "upTime": "2023-05-07 03:13", "key": 388}, {"symbol": "LABU", "barTime": "2023-04-17 23:30", "content": "SELL@5.83 Size:71 Gain:-0.01%", "strategy": "Revival (BUY:SMA30 SELL:BollTop TF:60)", "upTime": "2023-05-07 03:49", "key": 389}, {"symbol": "KO", "barTime": "2023-04-17 23:30", "content": "SELL@63.27 Size:7 Gain:6.16%", "strategy": "Revival (BUY:SMA30 SELL:BollTop TF:60)", "upTime": "2023-05-07 03:49", "key": 390}, {"symbol": "LABU", "barTime": "2023-04-17 23:30", "content": "SELL@5.83 Size:71 Gain:-11.94%", "strategy": "Vivid (BollBot x BollTop TF:60)", "upTime": "2023-05-07 03:30", "key": 391}, {"symbol": "MNST", "barTime": "2023-04-17 23:30", "content": "SELL@52.79 Size:3 Gain:1.05%", "strategy": "Vivid (BollBot x BollTop TF:60)", "upTime": "2023-05-07 03:30", "key": 392}, {"symbol": "KO", "barTime": "2023-04-17 23:30", "content": "SELL@63.27 Size:0 Gain:0.00%", "strategy": "Vivid (BollBot x BollTop TF:60)", "upTime": "2023-05-07 03:30", "key": 393}, {"symbol": "MNST", "barTime": "2023-04-17 22:30", "content": "SELL@52.91 Size:8 Gain:3.87%", "strategy": "Revival (BUY:SMA30 SELL:BollTop TF:60)", "upTime": "2023-05-07 03:49", "key": 394}, {"symbol": "NUGT", "barTime": "2023-04-17 22:30", "content": "BUY@46.84 Size:10", "strategy": "Vivid (BollBot x BollTop TF:60)", "upTime": "2023-05-07 03:49", "key": 395}, {"symbol": "TSLA", "barTime": "2023-04-17 21:30", "content": "BUY@184.64 Size:2", "strategy": "Revival (BUY:SMA30 SELL:BollTop TF:60)", "upTime": "2023-05-07 03:37", "key": 396}, {"symbol": "TCEHY", "barTime": "2023-04-17 21:30", "content": "BUY@46.60 Size:10", "strategy": "Revival (BUY:SMA30 SELL:BollTop TF:60)", "upTime": "2023-05-07 03:13", "key": 397}, {"symbol": "MSFT", "barTime": "2023-04-15 03:30", "content": "BUY@283.28 Size:1", "strategy": "Revival (BUY:SMA30 SELL:BollTop TF:60)", "upTime": "2023-05-07 03:13", "key": 398}, {"symbol": "NUGT", "barTime": "2023-04-15 03:30", "content": "BUY@48.49 Size:10", "strategy": "Revival (BUY:SMA30 SELL:BollTop TF:60)", "upTime": "2023-05-07 03:49", "key": 399}, {"symbol": "QQQ", "barTime": "2023-04-15 01:30", "content": "BUY@314.74 Size:1", "strategy": "Revival (BUY:SMA30 SELL:BollTop TF:60)", "upTime": "2023-05-07 03:13", "key": 400}, {"symbol": "NVDA", "barTime": "2023-04-15 01:30", "content": "BUY@263.80 Size:1", "strategy": "Vivid (BollBot x BollTop TF:60)", "upTime": "2023-05-07 03:49", "key": 401}, {"symbol": "TQQQ", "barTime": "2023-04-15 01:30", "content": "BUY@27.02 Size:18", "strategy": "Revival (BUY:SMA30 SELL:BollTop TF:60)", "upTime": "2023-05-07 03:49", "key": 402}, {"symbol": "UPRO", "barTime": "2023-04-15 01:30", "content": "BUY@38.68 Size:12", "strategy": "Revival (BUY:SMA30 SELL:BollTop TF:60)", "upTime": "2023-05-07 03:49", "key": 403}, {"symbol": "LABU", "barTime": "2023-04-15 01:30", "content": "BUY@5.07 Size:98", "strategy": "Revival (BUY:SMA30 SELL:BollTop TF:60)", "upTime": "2023-05-07 03:49", "key": 404}, {"symbol": "MNST", "barTime": "2023-04-15 01:30", "content": "BUY@51.96 Size:9", "strategy": "Revival (BUY:SMA30 SELL:BollTop TF:60)", "upTime": "2023-05-07 03:49", "key": 405}, {"symbol": "NUGT", "barTime": "2023-04-15 01:30", "content": "BUY@48.18 Size:10", "strategy": "Revival (BUY:SMA30 SELL:BollTop TF:60)", "upTime": "2023-05-07 03:49", "key": 406}, {"symbol": "ASML", "barTime": "2023-04-15 01:30", "content": "BUY@659.61 Size:0", "strategy": "Revival (BUY:SMA30 SELL:BollTop TF:60)", "upTime": "2023-05-07 03:13", "key": 407}, {"symbol": "SMH", "barTime": "2023-04-15 01:30", "content": "BUY@124.62 Size:4", "strategy": "Vivid (BollBot x BollTop TF:60)", "upTime": "2023-05-07 03:30", "key": 408}, {"symbol": "SOXL", "barTime": "2023-04-15 01:30", "content": "BUY@15.39 Size:32", "strategy": "Vivid (BollBot x BollTop TF:60)", "upTime": "2023-05-07 03:49", "key": 409}, {"symbol": "EDU", "barTime": "2023-04-14 23:30", "content": "BUY@37.00 Size:13", "strategy": "Revival (BUY:SMA30 SELL:BollTop TF:60)", "upTime": "2023-05-07 03:49", "key": 410}, {"symbol": "MSFT", "barTime": "2023-04-14 22:30", "content": "BUY@283.52 Size:1", "strategy": "Revival (BUY:SMA30 SELL:BollTop TF:60)", "upTime": "2023-05-07 03:13", "key": 411}, {"symbol": "AAPL", "barTime": "2023-04-14 21:30", "content": "SELL@164.97 Size:2 Gain:2.78%", "strategy": "Vivid (BollBot x BollTop TF:60)", "upTime": "2023-05-07 03:49", "key": 412}, {"symbol": "EDU", "barTime": "2023-04-14 21:30", "content": "BUY@36.93 Size:13", "strategy": "Revival (BUY:SMA30 SELL:BollTop TF:60)", "upTime": "2023-05-07 03:49", "key": 413}, {"symbol": "KO", "barTime": "2023-04-14 21:30", "content": "SELL@62.86 Size:7 Gain:5.48%", "strategy": "Revival (BUY:SMA30 SELL:BollTop TF:60)", "upTime": "2023-05-07 03:49", "key": 414}, {"symbol": "MSFT", "barTime": "2023-04-14 21:30", "content": "SELL@286.09 Size:0 Gain:0.00%", "strategy": "Vivid (BollBot x BollTop TF:60)", "upTime": "2023-05-07 03:13", "key": 415}, {"symbol": "MNST", "barTime": "2023-04-14 21:30", "content": "SELL@52.44 Size:8 Gain:0.38%", "strategy": "Vivid (BollBot x BollTop TF:60)", "upTime": "2023-05-07 03:30", "key": 416}, {"symbol": "KO", "barTime": "2023-04-14 21:30", "content": "SELL@62.86 Size:0 Gain:0.00%", "strategy": "Vivid (BollBot x BollTop TF:60)", "upTime": "2023-05-07 03:30", "key": 417}, {"symbol": "AAPL", "barTime": "2023-04-14 03:30", "content": "SELL@165.56 Size:2 Gain:7.38%", "strategy": "Revival (BUY:SMA30 SELL:BollTop TF:60)", "upTime": "2023-05-07 03:49", "key": 418}, {"symbol": "QQQ", "barTime": "2023-04-14 03:30", "content": "SELL@319.17 Size:0 Gain:0.00%", "strategy": "Vivid (BollBot x BollTop TF:60)", "upTime": "2023-05-07 03:13", "key": 419}, {"symbol": "AMZN", "barTime": "2023-04-14 03:30", "content": "SELL@102.40 Size:4 Gain:3.94%", "strategy": "Vivid (BollBot x BollTop TF:60)", "upTime": "2023-05-07 03:49", "key": 420}, {"symbol": "UPRO", "barTime": "2023-04-14 03:30", "content": "SELL@39.51 Size:10 Gain:7.01%", "strategy": "Revival (BUY:SMA30 SELL:BollTop TF:60)", "upTime": "2023-05-07 03:49", "key": 421}, {"symbol": "SSO", "barTime": "2023-04-14 03:30", "content": "SELL@51.08 Size:8 Gain:5.52%", "strategy": "Revival (BUY:SMA30 SELL:BollTop TF:60)", "upTime": "2023-05-07 03:13", "key": 422}, {"symbol": "META", "barTime": "2023-04-14 03:30", "content": "SELL@220.35 Size:2 Gain:21.71%", "strategy": "Vivid (BollBot x BollTop TF:60)", "upTime": "2023-05-07 03:49", "key": 423}, {"symbol": "GOOGL", "barTime": "2023-04-14 03:30", "content": "SELL@107.43 Size:0 Gain:0.00%", "strategy": "Vivid (BollBot x BollTop TF:60)", "upTime": "2023-05-07 03:13", "key": 424}, {"symbol": "UPRO", "barTime": "2023-04-14 03:30", "content": "SELL@39.51 Size:10 Gain:13.51%", "strategy": "Vivid (BollBot x BollTop TF:60)", "upTime": "2023-05-07 03:49", "key": 425}, {"symbol": "SSO", "barTime": "2023-04-14 03:30", "content": "SELL@51.08 Size:0 Gain:0.00%", "strategy": "Vivid (BollBot x BollTop TF:60)", "upTime": "2023-05-07 03:13", "key": 426}, {"symbol": "NKE", "barTime": "2023-04-14 03:30", "content": "SELL@126.43 Size:0 Gain:0.00%", "strategy": "Vivid (BollBot x BollTop TF:60)", "upTime": "2023-05-07 03:13", "key": 427}, {"symbol": "META", "barTime": "2023-04-14 02:30", "content": "SELL@220.02 Size:2 Gain:3.95%", "strategy": "Revival (BUY:SMA30 SELL:BollTop TF:60)", "upTime": "2023-05-07 03:49", "key": 428}, {"symbol": "TQQQ", "barTime": "2023-04-14 02:30", "content": "SELL@27.69 Size:15 Gain:15.13%", "strategy": "Vivid (BollBot x BollTop TF:60)", "upTime": "2023-05-07 03:49", "key": 429}, {"symbol": "LABU", "barTime": "2023-04-14 02:30", "content": "SELL@5.50 Size:76 Gain:-17.07%", "strategy": "Vivid (BollBot x BollTop TF:60)", "upTime": "2023-05-07 03:30", "key": 430}, {"symbol": "MNST", "barTime": "2023-04-14 02:30", "content": "SELL@52.76 Size:8 Gain:0.99%", "strategy": "Vivid (BollBot x BollTop TF:60)", "upTime": "2023-05-07 03:30", "key": 431}, {"symbol": "NUGT", "barTime": "2023-04-14 02:30", "content": "SELL@51.31 Size:8 Gain:29.32%", "strategy": "Vivid (BollBot x BollTop TF:60)", "upTime": "2023-05-07 03:49", "key": 432}, {"symbol": "TSLA", "barTime": "2023-04-14 01:30", "content": "BUY@184.13 Size:2", "strategy": "Revival (BUY:SMA30 SELL:BollTop TF:60)", "upTime": "2023-05-07 03:37", "key": 433}, {"symbol": "LABU", "barTime": "2023-04-14 01:30", "content": "SELL@5.50 Size:76 Gain:-7.41%", "strategy": "Revival (BUY:SMA30 SELL:BollTop TF:60)", "upTime": "2023-05-07 03:49", "key": 434}, {"symbol": "MSFT", "barTime": "2023-04-14 01:30", "content": "SELL@288.63 Size:0 Gain:0.00%", "strategy": "Vivid (BollBot x BollTop TF:60)", "upTime": "2023-05-07 03:13", "key": 435}, {"symbol": "KO", "barTime": "2023-04-14 00:30", "content": "BUY@62.12 Size:8", "strategy": "Revival (BUY:SMA30 SELL:BollTop TF:60)", "upTime": "2023-05-07 03:49", "key": 436}, {"symbol": "NFLX", "barTime": "2023-04-14 00:30", "content": "SELL@345.48 Size:1 Gain:8.66%", "strategy": "Vivid (BollBot x BollTop TF:60)", "upTime": "2023-05-07 03:13", "key": 437}, {"symbol": "MNST", "barTime": "2023-04-13 23:30", "content": "BUY@51.94 Size:9", "strategy": "Revival (BUY:SMA30 SELL:BollTop TF:60)", "upTime": "2023-05-07 03:49", "key": 438}, {"symbol": "NUGT", "barTime": "2023-04-13 23:30", "content": "SELL@50.74 Size:8 Gain:8.01%", "strategy": "Revival (BUY:SMA30 SELL:BollTop TF:60)", "upTime": "2023-05-07 03:49", "key": 439}, {"symbol": "GOOGL", "barTime": "2023-04-13 23:30", "content": "SELL@106.67 Size:0 Gain:0.00%", "strategy": "Vivid (BollBot x BollTop TF:60)", "upTime": "2023-05-07 03:13", "key": 440}, {"symbol": "LRCX", "barTime": "2023-04-13 23:30", "content": "BUY@492.94 Size:1", "strategy": "Vivid (BollBot x BollTop TF:60)", "upTime": "2023-05-07 03:49", "key": 441}, {"symbol": "TSLA", "barTime": "2023-04-13 22:30", "content": "BUY@184.17 Size:2", "strategy": "Revival (BUY:SMA30 SELL:BollTop TF:60)", "upTime": "2023-05-07 03:37", "key": 442}, {"symbol": "QQQ", "barTime": "2023-04-13 21:30", "content": "BUY@314.07 Size:1", "strategy": "Revival (BUY:SMA30 SELL:BollTop TF:60)", "upTime": "2023-05-07 03:13", "key": 443}, {"symbol": "AAPL", "barTime": "2023-04-13 21:30", "content": "BUY@161.80 Size:3", "strategy": "Revival (BUY:SMA30 SELL:BollTop TF:60)", "upTime": "2023-05-07 03:49", "key": 444}, {"symbol": "AMZN", "barTime": "2023-04-13 21:30", "content": "BUY@99.50 Size:5", "strategy": "Revival (BUY:SMA30 SELL:BollTop TF:60)", "upTime": "2023-05-07 03:49", "key": 445}, {"symbol": "TSLA", "barTime": "2023-04-13 21:30", "content": "BUY@182.70 Size:2", "strategy": "Vivid (BollBot x BollTop TF:60)", "upTime": "2023-05-07 03:49", "key": 446}, {"symbol": "QQQ", "barTime": "2023-04-13 21:30", "content": "BUY@314.07 Size:1", "strategy": "Vivid (BollBot x BollTop TF:60)", "upTime": "2023-05-07 03:13", "key": 447}, {"symbol": "AAPL", "barTime": "2023-04-13 21:30", "content": "BUY@161.80 Size:3", "strategy": "Vivid (BollBot x BollTop TF:60)", "upTime": "2023-05-07 03:49", "key": 448}, {"symbol": "NVDA", "barTime": "2023-04-13 21:30", "content": "BUY@264.85 Size:1", "strategy": "Vivid (BollBot x BollTop TF:60)", "upTime": "2023-05-07 03:49", "key": 449}, {"symbol": "META", "barTime": "2023-04-13 21:30", "content": "BUY@216.54 Size:2", "strategy": "Revival (BUY:SMA30 SELL:BollTop TF:60)", "upTime": "2023-05-07 03:49", "key": 450}, {"symbol": "MSFT", "barTime": "2023-04-13 21:30", "content": "BUY@284.85 Size:1", "strategy": "Revival (BUY:SMA30 SELL:BollTop TF:60)", "upTime": "2023-05-07 03:13", "key": 451}, {"symbol": "GOOGL", "barTime": "2023-04-13 21:30", "content": "BUY@105.73 Size:4", "strategy": "Revival (BUY:SMA30 SELL:BollTop TF:60)", "upTime": "2023-05-07 03:13", "key": 452}, {"symbol": "TQQQ", "barTime": "2023-04-13 21:30", "content": "BUY@26.87 Size:18", "strategy": "Revival (BUY:SMA30 SELL:BollTop TF:60)", "upTime": "2023-05-07 03:49", "key": 453}, {"symbol": "UPRO", "barTime": "2023-04-13 21:30", "content": "BUY@38.37 Size:13", "strategy": "Revival (BUY:SMA30 SELL:BollTop TF:60)", "upTime": "2023-05-07 03:49", "key": 454}, {"symbol": "LABU", "barTime": "2023-04-13 21:30", "content": "BUY@5.24 Size:95", "strategy": "Revival (BUY:SMA30 SELL:BollTop TF:60)", "upTime": "2023-05-07 03:49", "key": 455}, {"symbol": "SSO", "barTime": "2023-04-13 21:30", "content": "BUY@49.91 Size:10", "strategy": "Revival (BUY:SMA30 SELL:BollTop TF:60)", "upTime": "2023-05-07 03:13", "key": 456}, {"symbol": "NFLX", "barTime": "2023-04-13 21:30", "content": "BUY@339.34 Size:1", "strategy": "Revival (BUY:SMA30 SELL:BollTop TF:60)", "upTime": "2023-05-07 03:13", "key": 457}, {"symbol": "ASML", "barTime": "2023-04-13 21:30", "content": "BUY@659.03 Size:0", "strategy": "Revival (BUY:SMA30 SELL:BollTop TF:60)", "upTime": "2023-05-07 03:13", "key": 458}, {"symbol": "SMH", "barTime": "2023-04-13 21:30", "content": "BUY@124.47 Size:4", "strategy": "Vivid (BollBot x BollTop TF:60)", "upTime": "2023-05-07 03:30", "key": 459}, {"symbol": "SOXL", "barTime": "2023-04-13 21:30", "content": "BUY@15.30 Size:32", "strategy": "Vivid (BollBot x BollTop TF:60)", "upTime": "2023-05-07 03:49", "key": 460}, {"symbol": "TQQQ", "barTime": "2023-04-13 21:30", "content": "BUY@26.87 Size:18", "strategy": "Vivid (BollBot x BollTop TF:60)", "upTime": "2023-05-07 03:49", "key": 461}, {"symbol": "NFLX", "barTime": "2023-04-13 21:30", "content": "BUY@339.34 Size:1", "strategy": "Vivid (BollBot x BollTop TF:60)", "upTime": "2023-05-07 03:13", "key": 462}, {"symbol": "ASML", "barTime": "2023-04-13 21:30", "content": "BUY@659.03 Size:0", "strategy": "Vivid (BollBot x BollTop TF:60)", "upTime": "2023-05-07 03:13", "key": 463}, {"symbol": "AMZN", "barTime": "2023-04-13 03:30", "content": "BUY@96.85 Size:5", "strategy": "Vivid (BollBot x BollTop TF:60)", "upTime": "2023-05-07 03:49", "key": 464}, {"symbol": "MNST", "barTime": "2023-04-13 03:30", "content": "BUY@51.95 Size:9", "strategy": "Revival (BUY:SMA30 SELL:BollTop TF:60)", "upTime": "2023-05-07 03:49", "key": 465}, {"symbol": "KO", "barTime": "2023-04-13 03:30", "content": "BUY@62.06 Size:8", "strategy": "Revival (BUY:SMA30 SELL:BollTop TF:60)", "upTime": "2023-05-07 03:49", "key": 466}, {"symbol": "GOOGL", "barTime": "2023-04-13 03:30", "content": "BUY@103.59 Size:4", "strategy": "Vivid (BollBot x BollTop TF:60)", "upTime": "2023-05-07 03:13", "key": 467}, {"symbol": "UPRO", "barTime": "2023-04-13 03:30", "content": "BUY@37.70 Size:13", "strategy": "Vivid (BollBot x BollTop TF:60)", "upTime": "2023-05-07 03:49", "key": 468}, {"symbol": "SSO", "barTime": "2023-04-13 03:30", "content": "BUY@49.31 Size:10", "strategy": "Vivid (BollBot x BollTop TF:60)", "upTime": "2023-05-07 03:13", "key": 469}, {"symbol": "EDU", "barTime": "2023-04-13 03:30", "content": "BUY@35.88 Size:13", "strategy": "Vivid (BollBot x BollTop TF:60)", "upTime": "2023-05-07 03:49", "key": 470}, {"symbol": "TCEHY", "barTime": "2023-04-13 02:30", "content": "BUY@44.04 Size:11", "strategy": "Vivid (BollBot x BollTop TF:60)", "upTime": "2023-05-07 03:13", "key": 471}, {"symbol": "MNST", "barTime": "2023-04-13 01:30", "content": "SELL@52.56 Size:8 Gain:3.18%", "strategy": "Revival (BUY:SMA30 SELL:BollTop TF:60)", "upTime": "2023-05-07 03:49", "key": 472}, {"symbol": "MNST", "barTime": "2023-04-13 01:30", "content": "SELL@52.56 Size:8 Gain:0.61%", "strategy": "Vivid (BollBot x BollTop TF:60)", "upTime": "2023-05-07 03:30", "key": 473}, {"symbol": "KO", "barTime": "2023-04-13 01:30", "content": "SELL@62.75 Size:0 Gain:0.00%", "strategy": "Vivid (BollBot x BollTop TF:60)", "upTime": "2023-05-07 03:30", "key": 474}, {"symbol": "MSFT", "barTime": "2023-04-13 00:30", "content": "BUY@283.73 Size:1", "strategy": "Revival (BUY:SMA30 SELL:BollTop TF:60)", "upTime": "2023-05-07 03:13", "key": 475}, {"symbol": "EDU", "barTime": "2023-04-13 00:30", "content": "BUY@36.34 Size:13", "strategy": "Vivid (BollBot x BollTop TF:60)", "upTime": "2023-05-07 03:49", "key": 476}, {"symbol": "NVDA", "barTime": "2023-04-12 23:30", "content": "BUY@266.84 Size:1", "strategy": "Vivid (BollBot x BollTop TF:60)", "upTime": "2023-05-07 03:49", "key": 477}, {"symbol": "AMZN", "barTime": "2023-04-12 23:30", "content": "BUY@98.12 Size:5", "strategy": "Vivid (BollBot x BollTop TF:60)", "upTime": "2023-05-07 03:49", "key": 478}, {"symbol": "SMH", "barTime": "2023-04-12 23:30", "content": "BUY@125.66 Size:3", "strategy": "Revival (BUY:SMA30 SELL:BollTop TF:60)", "upTime": "2023-05-07 03:30", "key": 479}, {"symbol": "SOXL", "barTime": "2023-04-12 23:30", "content": "BUY@15.84 Size:31", "strategy": "Revival (BUY:SMA30 SELL:BollTop TF:60)", "upTime": "2023-05-07 03:30", "key": 480}, {"symbol": "MNST", "barTime": "2023-04-12 22:30", "content": "BUY@52.10 Size:9", "strategy": "Revival (BUY:SMA30 SELL:BollTop TF:60)", "upTime": "2023-05-07 03:49", "key": 481}, {"symbol": "NKE", "barTime": "2023-04-12 22:30", "content": "SELL@123.67 Size:0 Gain:0.00%", "strategy": "Vivid (BollBot x BollTop TF:60)", "upTime": "2023-05-07 03:13", "key": 482}, {"symbol": "QQQ", "barTime": "2023-04-12 21:30", "content": "BUY@313.75 Size:1", "strategy": "Revival (BUY:SMA30 SELL:BollTop TF:60)", "upTime": "2023-05-07 03:13", "key": 483}, {"symbol": "TQQQ", "barTime": "2023-04-12 21:30", "content": "BUY@26.83 Size:18", "strategy": "Revival (BUY:SMA30 SELL:BollTop TF:60)", "upTime": "2023-05-07 03:49", "key": 484}, {"symbol": "ASML", "barTime": "2023-04-12 21:30", "content": "BUY@659.21 Size:0", "strategy": "Revival (BUY:SMA30 SELL:BollTop TF:60)", "upTime": "2023-05-07 03:13", "key": 485}, {"symbol": "KO", "barTime": "2023-04-12 21:30", "content": "BUY@62.14 Size:8", "strategy": "Revival (BUY:SMA30 SELL:BollTop TF:60)", "upTime": "2023-05-07 03:49", "key": 486}, {"symbol": "NKE", "barTime": "2023-04-12 03:30", "content": "SELL@123.30 Size:0 Gain:0.00%", "strategy": "Vivid (BollBot x BollTop TF:60)", "upTime": "2023-05-07 03:13", "key": 487}, {"symbol": "TCEHY", "barTime": "2023-04-12 02:30", "content": "BUY@47.03 Size:10", "strategy": "Vivid (BollBot x BollTop TF:60)", "upTime": "2023-05-07 03:13", "key": 488}, {"symbol": "QQQ", "barTime": "2023-04-12 01:30", "content": "BUY@313.88 Size:1", "strategy": "Revival (BUY:SMA30 SELL:BollTop TF:60)", "upTime": "2023-05-07 03:13", "key": 489}, {"symbol": "TQQQ", "barTime": "2023-04-12 01:30", "content": "BUY@26.88 Size:18", "strategy": "Revival (BUY:SMA30 SELL:BollTop TF:60)", "upTime": "2023-05-07 03:49", "key": 490}, {"symbol": "AMZN", "barTime": "2023-04-12 00:30", "content": "BUY@98.93 Size:5", "strategy": "Vivid (BollBot x BollTop TF:60)", "upTime": "2023-05-07 03:49", "key": 491}, {"symbol": "GOOGL", "barTime": "2023-04-12 00:30", "content": "BUY@104.63 Size:4", "strategy": "Revival (BUY:SMA30 SELL:BollTop TF:60)", "upTime": "2023-05-07 03:13", "key": 492}, {"symbol": "NKE", "barTime": "2023-04-12 00:30", "content": "SELL@123.07 Size:3 Gain:3.04%", "strategy": "Revival (BUY:SMA30 SELL:BollTop TF:60)", "upTime": "2023-05-07 03:13", "key": 493}, {"symbol": "NUGT", "barTime": "2023-04-12 00:30", "content": "SELL@47.89 Size:9 Gain:20.69%", "strategy": "Vivid (BollBot x BollTop TF:60)", "upTime": "2023-05-07 03:49", "key": 494}, {"symbol": "NKE", "barTime": "2023-04-12 00:30", "content": "SELL@123.07 Size:0 Gain:0.00%", "strategy": "Vivid (BollBot x BollTop TF:60)", "upTime": "2023-05-07 03:13", "key": 495}, {"symbol": "TSLA", "barTime": "2023-04-11 23:30", "content": "SELL@187.28 Size:2 Gain:2.17%", "strategy": "Vivid (BollBot x BollTop TF:60)", "upTime": "2023-05-07 03:49", "key": 496}, {"symbol": "NUGT", "barTime": "2023-04-11 23:30", "content": "SELL@48.59 Size:8 Gain:3.43%", "strategy": "Revival (BUY:SMA30 SELL:BollTop TF:60)", "upTime": "2023-05-07 03:49", "key": 497}, {"symbol": "SMH", "barTime": "2023-04-11 22:30", "content": "SELL@127.89 Size:3 Gain:4.50%", "strategy": "Revival (BUY:SMA30 SELL:BollTop TF:60)", "upTime": "2023-05-07 03:30", "key": 498}, {"symbol": "SOXL", "barTime": "2023-04-11 22:30", "content": "SELL@16.37 Size:25 Gain:3.60%", "strategy": "Revival (BUY:SMA30 SELL:BollTop TF:60)", "upTime": "2023-05-07 03:30", "key": 499}, {"symbol": "ASML", "barTime": "2023-04-11 22:30", "content": "SELL@667.37 Size:0 Gain:0.00%", "strategy": "Revival (BUY:SMA30 SELL:BollTop TF:60)", "upTime": "2023-05-07 03:13", "key": 500}, {"symbol": "NKE", "barTime": "2023-04-11 22:30", "content": "SELL@122.73 Size:3 Gain:2.75%", "strategy": "Revival (BUY:SMA30 SELL:BollTop TF:60)", "upTime": "2023-05-07 03:13", "key": 501}, {"symbol": "KO", "barTime": "2023-04-11 22:30", "content": "BUY@61.98 Size:8", "strategy": "Revival (BUY:SMA30 SELL:BollTop TF:60)", "upTime": "2023-05-07 03:49", "key": 502}, {"symbol": "SMH", "barTime": "2023-04-11 22:30", "content": "SELL@127.89 Size:3 Gain:0.93%", "strategy": "Vivid (BollBot x BollTop TF:60)", "upTime": "2023-05-07 03:30", "key": 503}, {"symbol": "SOXL", "barTime": "2023-04-11 22:30", "content": "SELL@16.37 Size:25 Gain:1.31%", "strategy": "Vivid (BollBot x BollTop TF:60)", "upTime": "2023-05-07 03:49", "key": 504}, {"symbol": "LRCX", "barTime": "2023-04-11 22:30", "content": "SELL@508.08 Size:1 Gain:3.25%", "strategy": "Vivid (BollBot x BollTop TF:60)", "upTime": "2023-05-07 03:49", "key": 505}, {"symbol": "NFLX", "barTime": "2023-04-11 22:30", "content": "SELL@340.60 Size:1 Gain:7.13%", "strategy": "Vivid (BollBot x BollTop TF:60)", "upTime": "2023-05-07 03:13", "key": 506}, {"symbol": "ASML", "barTime": "2023-04-11 22:30", "content": "SELL@667.37 Size:0 Gain:0.00%", "strategy": "Vivid (BollBot x BollTop TF:60)", "upTime": "2023-05-07 03:13", "key": 507}, {"symbol": "TSLA", "barTime": "2023-04-11 21:30", "content": "BUY@184.99 Size:2", "strategy": "Revival (BUY:SMA30 SELL:BollTop TF:60)", "upTime": "2023-05-07 03:37", "key": 508}, {"symbol": "NFLX", "barTime": "2023-04-11 21:30", "content": "BUY@339.57 Size:1", "strategy": "Revival (BUY:SMA30 SELL:BollTop TF:60)", "upTime": "2023-05-07 03:13", "key": 509}, {"symbol": "NUGT", "barTime": "2023-04-11 21:30", "content": "BUY@48.32 Size:10", "strategy": "Revival (BUY:SMA30 SELL:BollTop TF:60)", "upTime": "2023-05-07 03:49", "key": 510}, {"symbol": "ASML", "barTime": "2023-04-11 21:30", "content": "BUY@664.40 Size:0", "strategy": "Revival (BUY:SMA30 SELL:BollTop TF:60)", "upTime": "2023-05-07 03:13", "key": 511}, {"symbol": "AMZN", "barTime": "2023-04-11 03:30", "content": "BUY@101.15 Size:4", "strategy": "Revival (BUY:SMA30 SELL:BollTop TF:60)", "upTime": "2023-05-07 03:49", "key": 512}, {"symbol": "NVDA", "barTime": "2023-04-11 03:30", "content": "SELL@275.79 Size:1 Gain:2.79%", "strategy": "Vivid (BollBot x BollTop TF:60)", "upTime": "2023-05-07 03:49", "key": 513}, {"symbol": "SOXL", "barTime": "2023-04-11 03:30", "content": "SELL@16.39 Size:25 Gain:3.73%", "strategy": "Revival (BUY:SMA30 SELL:BollTop TF:60)", "upTime": "2023-05-07 03:30", "key": 514}, {"symbol": "TQQQ", "barTime": "2023-04-11 03:30", "content": "BUY@27.10 Size:18", "strategy": "Revival (BUY:SMA30 SELL:BollTop TF:60)", "upTime": "2023-05-07 03:49", "key": 515}, {"symbol": "LABU", "barTime": "2023-04-11 03:30", "content": "BUY@4.76 Size:105", "strategy": "Revival (BUY:SMA30 SELL:BollTop TF:60)", "upTime": "2023-05-07 03:49", "key": 516}, {"symbol": "LRCX", "barTime": "2023-04-11 03:30", "content": "SELL@507.46 Size:1 Gain:3.88%", "strategy": "Revival (BUY:SMA30 SELL:BollTop TF:60)", "upTime": "2023-05-07 03:49", "key": 517}, {"symbol": "KO", "barTime": "2023-04-11 03:30", "content": "BUY@62.06 Size:8", "strategy": "Revival (BUY:SMA30 SELL:BollTop TF:60)", "upTime": "2023-05-07 03:49", "key": 518}, {"symbol": "LRCX", "barTime": "2023-04-11 03:30", "content": "SELL@507.46 Size:1 Gain:3.12%", "strategy": "Vivid (BollBot x BollTop TF:60)", "upTime": "2023-05-07 03:49", "key": 519}, {"symbol": "NKE", "barTime": "2023-04-11 02:30", "content": "BUY@120.39 Size:4", "strategy": "Revival (BUY:SMA30 SELL:BollTop TF:60)", "upTime": "2023-05-07 03:13", "key": 520}, {"symbol": "QQQ", "barTime": "2023-04-11 01:30", "content": "BUY@314.19 Size:1", "strategy": "Revival (BUY:SMA30 SELL:BollTop TF:60)", "upTime": "2023-05-07 03:13", "key": 521}, {"symbol": "AMZN", "barTime": "2023-04-11 01:30", "content": "BUY@100.86 Size:4", "strategy": "Revival (BUY:SMA30 SELL:BollTop TF:60)", "upTime": "2023-05-07 03:49", "key": 522}, {"symbol": "SMH", "barTime": "2023-04-11 01:30", "content": "BUY@126.49 Size:3", "strategy": "Revival (BUY:SMA30 SELL:BollTop TF:60)", "upTime": "2023-05-07 03:30", "key": 523}, {"symbol": "SOXL", "barTime": "2023-04-11 01:30", "content": "BUY@16.17 Size:30", "strategy": "Revival (BUY:SMA30 SELL:BollTop TF:60)", "upTime": "2023-05-07 03:30", "key": 524}, {"symbol": "TQQQ", "barTime": "2023-04-11 01:30", "content": "BUY@26.97 Size:18", "strategy": "Revival (BUY:SMA30 SELL:BollTop TF:60)", "upTime": "2023-05-07 03:49", "key": 525}, {"symbol": "AAPL", "barTime": "2023-04-11 00:30", "content": "BUY@159.95 Size:3", "strategy": "Vivid (BollBot x BollTop TF:60)", "upTime": "2023-05-07 03:49", "key": 526}, {"symbol": "UPRO", "barTime": "2023-04-11 00:30", "content": "BUY@37.87 Size:13", "strategy": "Revival (BUY:SMA30 SELL:BollTop TF:60)", "upTime": "2023-05-07 03:49", "key": 527}, {"symbol": "SSO", "barTime": "2023-04-11 00:30", "content": "BUY@49.45 Size:10", "strategy": "Revival (BUY:SMA30 SELL:BollTop TF:60)", "upTime": "2023-05-07 03:13", "key": 528}, {"symbol": "LRCX", "barTime": "2023-04-11 00:30", "content": "BUY@499.79 Size:1", "strategy": "Revival (BUY:SMA30 SELL:BollTop TF:60)", "upTime": "2023-05-07 03:49", "key": 529}, {"symbol": "NKE", "barTime": "2023-04-11 00:30", "content": "BUY@120.26 Size:4", "strategy": "Revival (BUY:SMA30 SELL:BollTop TF:60)", "upTime": "2023-05-07 03:13", "key": 530}, {"symbol": "KO", "barTime": "2023-04-11 00:30", "content": "BUY@61.97 Size:8", "strategy": "Revival (BUY:SMA30 SELL:BollTop TF:60)", "upTime": "2023-05-07 03:49", "key": 531}, {"symbol": "NUGT", "barTime": "2023-04-11 00:30", "content": "BUY@45.33 Size:11", "strategy": "Vivid (BollBot x BollTop TF:60)", "upTime": "2023-05-07 03:49", "key": 532}, {"symbol": "META", "barTime": "2023-04-10 23:30", "content": "BUY@210.73 Size:2", "strategy": "Revival (BUY:SMA30 SELL:BollTop TF:60)", "upTime": "2023-05-07 03:49", "key": 533}, {"symbol": "NVDA", "barTime": "2023-04-10 22:30", "content": "BUY@270.67 Size:1", "strategy": "Revival (BUY:SMA30 SELL:BollTop TF:60)", "upTime": "2023-05-07 03:30", "key": 534}, {"symbol": "TSLA", "barTime": "2023-04-10 22:30", "content": "BUY@179.16 Size:2", "strategy": "Vivid (BollBot x BollTop TF:60)", "upTime": "2023-05-07 03:49", "key": 535}, {"symbol": "MSFT", "barTime": "2023-04-10 22:30", "content": "BUY@284.36 Size:1", "strategy": "Revival (BUY:SMA30 SELL:BollTop TF:60)", "upTime": "2023-05-07 03:13", "key": 536}, {"symbol": "NUGT", "barTime": "2023-04-10 22:30", "content": "BUY@45.64 Size:10", "strategy": "Revival (BUY:SMA30 SELL:BollTop TF:60)", "upTime": "2023-05-07 03:49", "key": 537}, {"symbol": "MNST", "barTime": "2023-04-10 22:30", "content": "BUY@51.51 Size:9", "strategy": "Vivid (BollBot x BollTop TF:60)", "upTime": "2023-05-07 03:30", "key": 538}, {"symbol": "NUGT", "barTime": "2023-04-10 22:30", "content": "BUY@45.64 Size:10", "strategy": "Vivid (BollBot x BollTop TF:60)", "upTime": "2023-05-07 03:49", "key": 539}, {"symbol": "ASML", "barTime": "2023-04-10 22:30", "content": "BUY@647.50 Size:0", "strategy": "Vivid (BollBot x BollTop TF:60)", "upTime": "2023-05-07 03:13", "key": 540}, {"symbol": "MSFT", "barTime": "2023-04-10 21:30", "content": "SELL@285.89 Size:0 Gain:0.00%", "strategy": "Vivid (BollBot x BollTop TF:60)", "upTime": "2023-05-07 03:13", "key": 541}, {"symbol": "GOOGL", "barTime": "2023-04-10 21:30", "content": "SELL@105.73 Size:0 Gain:0.00%", "strategy": "Vivid (BollBot x BollTop TF:60)", "upTime": "2023-05-07 03:13", "key": 542}], "updated": "2023-05-07 03:49:16", "timeframe": "60"}